[
    {
        "status": "completed", 
        "check_run_url": "https://api.github.com/repos/rbsheth/hunter/check-runs/1222121822", 
        "name": "jpeg-compressor analyze-cxx17 ubuntu-16.04", 
        "run_id": 293993383, 
        "url": "https://api.github.com/repos/rbsheth/hunter/actions/jobs/1222121822", 
        "html_url": "https://github.com/rbsheth/hunter/runs/1222121822", 
        "completed_at": "2020-10-07T18:29:53Z", 
        "run_url": "https://api.github.com/repos/rbsheth/hunter/actions/runs/293993383", 
        "node_id": "MDg6Q2hlY2tSdW4xMjIyMTIxODIy", 
        "steps": [
            {
                "status": "completed", 
                "name": "Set up job", 
                "number": 1, 
                "completed_at": "2020-10-07T18:29:12.000Z", 
                "started_at": "2020-10-07T18:29:10.000Z", 
                "conclusion": "success"
            }, 
            {
                "status": "completed", 
                "name": "Git checkout with submodules", 
                "number": 2, 
                "completed_at": "2020-10-07T18:29:16.000Z", 
                "started_at": "2020-10-07T18:29:12.000Z", 
                "conclusion": "success"
            }, 
            {
                "status": "completed", 
                "name": "Set up Python", 
                "number": 3, 
                "completed_at": "2020-10-07T18:29:16.000Z", 
                "started_at": "2020-10-07T18:29:16.000Z", 
                "conclusion": "success"
            }, 
            {
                "status": "completed", 
                "name": "Set up Python environment variable (Unix)", 
                "number": 4, 
                "completed_at": "2020-10-07T18:29:16.000Z", 
                "started_at": "2020-10-07T18:29:16.000Z", 
                "conclusion": "success"
            }, 
            {
                "status": "completed", 
                "name": "Set up Python environment variable (Windows)", 
                "number": 5, 
                "completed_at": "2020-10-07T18:29:16.000Z", 
                "started_at": "2020-10-07T18:29:16.000Z", 
                "conclusion": "skipped"
            }, 
            {
                "status": "completed", 
                "name": "Extract branch name", 
                "number": 6, 
                "completed_at": "2020-10-07T18:29:16.000Z", 
                "started_at": "2020-10-07T18:29:16.000Z", 
                "conclusion": "success"
            }, 
            {
                "status": "completed", 
                "name": "Upgrade pip", 
                "number": 7, 
                "completed_at": "2020-10-07T18:29:19.000Z", 
                "started_at": "2020-10-07T18:29:16.000Z", 
                "conclusion": "success"
            }, 
            {
                "status": "completed", 
                "name": "Build on Unix", 
                "number": 8, 
                "completed_at": "2020-10-07T18:29:53.000Z", 
                "started_at": "2020-10-07T18:29:19.000Z", 
                "conclusion": "failure"
            }, 
            {
                "status": "completed", 
                "name": "Build on Windows", 
                "number": 9, 
                "completed_at": "2020-10-07T18:29:53.000Z", 
                "started_at": "2020-10-07T18:29:53.000Z", 
                "conclusion": "skipped"
            }, 
            {
                "status": "completed", 
                "name": "Post Git checkout with submodules", 
                "number": 18, 
                "completed_at": "2020-10-07T18:29:53.000Z", 
                "started_at": "2020-10-07T18:29:53.000Z", 
                "conclusion": "success"
            }, 
            {
                "status": "completed", 
                "name": "Complete job", 
                "number": 19, 
                "completed_at": "2020-10-07T18:29:53.000Z", 
                "started_at": "2020-10-07T18:29:53.000Z", 
                "conclusion": "success"
            }
        ], 
        "head_sha": "abcb68288e4140d4b558bb7964f85bf78d45cb74", 
        "started_at": "2020-10-07T18:29:10Z", 
        "id": 1222121822, 
        "conclusion": "failure"
    }, 
    {
        "status": "completed", 
        "check_run_url": "https://api.github.com/repos/rbsheth/hunter/check-runs/1222121811", 
        "name": "jpeg-compressor android-ndk-r17-api-24-arm64-v8a-clang-libcxx14 ubuntu-16.04", 
        "run_id": 293993383, 
        "url": "https://api.github.com/repos/rbsheth/hunter/actions/jobs/1222121811", 
        "html_url": "https://github.com/rbsheth/hunter/runs/1222121811", 
        "completed_at": "2020-10-07T18:30:19Z", 
        "run_url": "https://api.github.com/repos/rbsheth/hunter/actions/runs/293993383", 
        "node_id": "MDg6Q2hlY2tSdW4xMjIyMTIxODEx", 
        "steps": [
            {
                "status": "completed", 
                "name": "Set up job", 
                "number": 1, 
                "completed_at": "2020-10-07T18:29:13.000Z", 
                "started_at": "2020-10-07T18:29:10.000Z", 
                "conclusion": "success"
            }, 
            {
                "status": "completed", 
                "name": "Git checkout with submodules", 
                "number": 2, 
                "completed_at": "2020-10-07T18:29:16.000Z", 
                "started_at": "2020-10-07T18:29:13.000Z", 
                "conclusion": "success"
            }, 
            {
                "status": "completed", 
                "name": "Set up Python", 
                "number": 3, 
                "completed_at": "2020-10-07T18:29:16.000Z", 
                "started_at": "2020-10-07T18:29:16.000Z", 
                "conclusion": "success"
            }, 
            {
                "status": "completed", 
                "name": "Set up Python environment variable (Unix)", 
                "number": 4, 
                "completed_at": "2020-10-07T18:29:16.000Z", 
                "started_at": "2020-10-07T18:29:16.000Z", 
                "conclusion": "success"
            }, 
            {
                "status": "completed", 
                "name": "Set up Python environment variable (Windows)", 
                "number": 5, 
                "completed_at": "2020-10-07T18:29:16.000Z", 
                "started_at": "2020-10-07T18:29:16.000Z", 
                "conclusion": "skipped"
            }, 
            {
                "status": "completed", 
                "name": "Extract branch name", 
                "number": 6, 
                "completed_at": "2020-10-07T18:29:16.000Z", 
                "started_at": "2020-10-07T18:29:16.000Z", 
                "conclusion": "success"
            }, 
            {
                "status": "completed", 
                "name": "Upgrade pip", 
                "number": 7, 
                "completed_at": "2020-10-07T18:29:17.000Z", 
                "started_at": "2020-10-07T18:29:16.000Z", 
                "conclusion": "success"
            }, 
            {
                "status": "completed", 
                "name": "Build on Unix", 
                "number": 8, 
                "completed_at": "2020-10-07T18:30:19.000Z", 
                "started_at": "2020-10-07T18:29:17.000Z", 
                "conclusion": "success"
            }, 
            {
                "status": "completed", 
                "name": "Build on Windows", 
                "number": 9, 
                "completed_at": "2020-10-07T18:30:19.000Z", 
                "started_at": "2020-10-07T18:30:19.000Z", 
                "conclusion": "skipped"
            }, 
            {
                "status": "completed", 
                "name": "Post Git checkout with submodules", 
                "number": 18, 
                "completed_at": "2020-10-07T18:30:19.000Z", 
                "started_at": "2020-10-07T18:30:19.000Z", 
                "conclusion": "success"
            }, 
            {
                "status": "completed", 
                "name": "Complete job", 
                "number": 19, 
                "completed_at": "2020-10-07T18:30:19.000Z", 
                "started_at": "2020-10-07T18:30:19.000Z", 
                "conclusion": "success"
            }
        ], 
        "head_sha": "abcb68288e4140d4b558bb7964f85bf78d45cb74", 
        "started_at": "2020-10-07T18:29:10Z", 
        "id": 1222121811, 
        "conclusion": "success"
    }, 
    {
        "status": "completed", 
        "check_run_url": "https://api.github.com/repos/rbsheth/hunter/check-runs/1222121746", 
        "name": "jpeg-compressor clang-cxx17 ubuntu-16.04", 
        "run_id": 293993383, 
        "url": "https://api.github.com/repos/rbsheth/hunter/actions/jobs/1222121746", 
        "html_url": "https://github.com/rbsheth/hunter/runs/1222121746", 
        "completed_at": "2020-10-07T18:29:39Z", 
        "run_url": "https://api.github.com/repos/rbsheth/hunter/actions/runs/293993383", 
        "node_id": "MDg6Q2hlY2tSdW4xMjIyMTIxNzQ2", 
        "steps": [
            {
                "status": "completed", 
                "name": "Set up job", 
                "number": 1, 
                "completed_at": "2020-10-07T18:29:12.000Z", 
                "started_at": "2020-10-07T18:29:10.000Z", 
                "conclusion": "success"
            }, 
            {
                "status": "completed", 
                "name": "Git checkout with submodules", 
                "number": 2, 
                "completed_at": "2020-10-07T18:29:15.000Z", 
                "started_at": "2020-10-07T18:29:12.000Z", 
                "conclusion": "success"
            }, 
            {
                "status": "completed", 
                "name": "Set up Python", 
                "number": 3, 
                "completed_at": "2020-10-07T18:29:15.000Z", 
                "started_at": "2020-10-07T18:29:15.000Z", 
                "conclusion": "success"
            }, 
            {
                "status": "completed", 
                "name": "Set up Python environment variable (Unix)", 
                "number": 4, 
                "completed_at": "2020-10-07T18:29:15.000Z", 
                "started_at": "2020-10-07T18:29:15.000Z", 
                "conclusion": "success"
            }, 
            {
                "status": "completed", 
                "name": "Set up Python environment variable (Windows)", 
                "number": 5, 
                "completed_at": "2020-10-07T18:29:15.000Z", 
                "started_at": "2020-10-07T18:29:15.000Z", 
                "conclusion": "skipped"
            }, 
            {
                "status": "completed", 
                "name": "Extract branch name", 
                "number": 6, 
                "completed_at": "2020-10-07T18:29:15.000Z", 
                "started_at": "2020-10-07T18:29:15.000Z", 
                "conclusion": "success"
            }, 
            {
                "status": "completed", 
                "name": "Upgrade pip", 
                "number": 7, 
                "completed_at": "2020-10-07T18:29:16.000Z", 
                "started_at": "2020-10-07T18:29:15.000Z", 
                "conclusion": "success"
            }, 
            {
                "status": "completed", 
                "name": "Build on Unix", 
                "number": 8, 
                "completed_at": "2020-10-07T18:29:39.000Z", 
                "started_at": "2020-10-07T18:29:16.000Z", 
                "conclusion": "success"
            }, 
            {
                "status": "completed", 
                "name": "Build on Windows", 
                "number": 9, 
                "completed_at": "2020-10-07T18:29:39.000Z", 
                "started_at": "2020-10-07T18:29:39.000Z", 
                "conclusion": "skipped"
            }, 
            {
                "status": "completed", 
                "name": "Post Git checkout with submodules", 
                "number": 18, 
                "completed_at": "2020-10-07T18:29:39.000Z", 
                "started_at": "2020-10-07T18:29:39.000Z", 
                "conclusion": "success"
            }, 
            {
                "status": "completed", 
                "name": "Complete job", 
                "number": 19, 
                "completed_at": "2020-10-07T18:29:39.000Z", 
                "started_at": "2020-10-07T18:29:39.000Z", 
                "conclusion": "success"
            }
        ], 
        "head_sha": "abcb68288e4140d4b558bb7964f85bf78d45cb74", 
        "started_at": "2020-10-07T18:29:10Z", 
        "id": 1222121746, 
        "conclusion": "success"
    }, 
    {
        "status": "completed", 
        "check_run_url": "https://api.github.com/repos/rbsheth/hunter/check-runs/1222121766", 
        "name": "jpeg-compressor gcc-7-cxx17 ubuntu-16.04", 
        "run_id": 293993383, 
        "url": "https://api.github.com/repos/rbsheth/hunter/actions/jobs/1222121766", 
        "html_url": "https://github.com/rbsheth/hunter/runs/1222121766", 
        "completed_at": "2020-10-07T18:29:46Z", 
        "run_url": "https://api.github.com/repos/rbsheth/hunter/actions/runs/293993383", 
        "node_id": "MDg6Q2hlY2tSdW4xMjIyMTIxNzY2", 
        "steps": [
            {
                "status": "completed", 
                "name": "Set up job", 
                "number": 1, 
                "completed_at": "2020-10-07T18:29:13.000Z", 
                "started_at": "2020-10-07T18:29:10.000Z", 
                "conclusion": "success"
            }, 
            {
                "status": "completed", 
                "name": "Git checkout with submodules", 
                "number": 2, 
                "completed_at": "2020-10-07T18:29:23.000Z", 
                "started_at": "2020-10-07T18:29:13.000Z", 
                "conclusion": "success"
            }, 
            {
                "status": "completed", 
                "name": "Set up Python", 
                "number": 3, 
                "completed_at": "2020-10-07T18:29:23.000Z", 
                "started_at": "2020-10-07T18:29:23.000Z", 
                "conclusion": "success"
            }, 
            {
                "status": "completed", 
                "name": "Set up Python environment variable (Unix)", 
                "number": 4, 
                "completed_at": "2020-10-07T18:29:23.000Z", 
                "started_at": "2020-10-07T18:29:23.000Z", 
                "conclusion": "success"
            }, 
            {
                "status": "completed", 
                "name": "Set up Python environment variable (Windows)", 
                "number": 5, 
                "completed_at": "2020-10-07T18:29:23.000Z", 
                "started_at": "2020-10-07T18:29:23.000Z", 
                "conclusion": "skipped"
            }, 
            {
                "status": "completed", 
                "name": "Extract branch name", 
                "number": 6, 
                "completed_at": "2020-10-07T18:29:23.000Z", 
                "started_at": "2020-10-07T18:29:23.000Z", 
                "conclusion": "success"
            }, 
            {
                "status": "completed", 
                "name": "Upgrade pip", 
                "number": 7, 
                "completed_at": "2020-10-07T18:29:24.000Z", 
                "started_at": "2020-10-07T18:29:23.000Z", 
                "conclusion": "success"
            }, 
            {
                "status": "completed", 
                "name": "Build on Unix", 
                "number": 8, 
                "completed_at": "2020-10-07T18:29:46.000Z", 
                "started_at": "2020-10-07T18:29:24.000Z", 
                "conclusion": "success"
            }, 
            {
                "status": "completed", 
                "name": "Build on Windows", 
                "number": 9, 
                "completed_at": "2020-10-07T18:29:46.000Z", 
                "started_at": "2020-10-07T18:29:46.000Z", 
                "conclusion": "skipped"
            }, 
            {
                "status": "completed", 
                "name": "Post Git checkout with submodules", 
                "number": 18, 
                "completed_at": "2020-10-07T18:29:46.000Z", 
                "started_at": "2020-10-07T18:29:46.000Z", 
                "conclusion": "success"
            }, 
            {
                "status": "completed", 
                "name": "Complete job", 
                "number": 19, 
                "completed_at": "2020-10-07T18:29:46.000Z", 
                "started_at": "2020-10-07T18:29:46.000Z", 
                "conclusion": "success"
            }
        ], 
        "head_sha": "abcb68288e4140d4b558bb7964f85bf78d45cb74", 
        "started_at": "2020-10-07T18:29:10Z", 
        "id": 1222121766, 
        "conclusion": "success"
    }, 
    {
        "status": "completed", 
        "check_run_url": "https://api.github.com/repos/rbsheth/hunter/check-runs/1222121782", 
        "name": "jpeg-compressor gcc-8-cxx17-fpic ubuntu-18.04", 
        "run_id": 293993383, 
        "url": "https://api.github.com/repos/rbsheth/hunter/actions/jobs/1222121782", 
        "html_url": "https://github.com/rbsheth/hunter/runs/1222121782", 
        "completed_at": "2020-10-07T18:29:47Z", 
        "run_url": "https://api.github.com/repos/rbsheth/hunter/actions/runs/293993383", 
        "node_id": "MDg6Q2hlY2tSdW4xMjIyMTIxNzgy", 
        "steps": [
            {
                "status": "completed", 
                "name": "Set up job", 
                "number": 1, 
                "completed_at": "2020-10-07T18:29:19.000Z", 
                "started_at": "2020-10-07T18:29:16.000Z", 
                "conclusion": "success"
            }, 
            {
                "status": "completed", 
                "name": "Git checkout with submodules", 
                "number": 2, 
                "completed_at": "2020-10-07T18:29:22.000Z", 
                "started_at": "2020-10-07T18:29:19.000Z", 
                "conclusion": "success"
            }, 
            {
                "status": "completed", 
                "name": "Set up Python", 
                "number": 3, 
                "completed_at": "2020-10-07T18:29:22.000Z", 
                "started_at": "2020-10-07T18:29:22.000Z", 
                "conclusion": "success"
            }, 
            {
                "status": "completed", 
                "name": "Set up Python environment variable (Unix)", 
                "number": 4, 
                "completed_at": "2020-10-07T18:29:22.000Z", 
                "started_at": "2020-10-07T18:29:22.000Z", 
                "conclusion": "success"
            }, 
            {
                "status": "completed", 
                "name": "Set up Python environment variable (Windows)", 
                "number": 5, 
                "completed_at": "2020-10-07T18:29:22.000Z", 
                "started_at": "2020-10-07T18:29:22.000Z", 
                "conclusion": "skipped"
            }, 
            {
                "status": "completed", 
                "name": "Extract branch name", 
                "number": 6, 
                "completed_at": "2020-10-07T18:29:22.000Z", 
                "started_at": "2020-10-07T18:29:22.000Z", 
                "conclusion": "success"
            }, 
            {
                "status": "completed", 
                "name": "Upgrade pip", 
                "number": 7, 
                "completed_at": "2020-10-07T18:29:26.000Z", 
                "started_at": "2020-10-07T18:29:22.000Z", 
                "conclusion": "success"
            }, 
            {
                "status": "completed", 
                "name": "Build on Unix", 
                "number": 8, 
                "completed_at": "2020-10-07T18:29:47.000Z", 
                "started_at": "2020-10-07T18:29:26.000Z", 
                "conclusion": "success"
            }, 
            {
                "status": "completed", 
                "name": "Build on Windows", 
                "number": 9, 
                "completed_at": "2020-10-07T18:29:47.000Z", 
                "started_at": "2020-10-07T18:29:47.000Z", 
                "conclusion": "skipped"
            }, 
            {
                "status": "completed", 
                "name": "Post Git checkout with submodules", 
                "number": 18, 
                "completed_at": "2020-10-07T18:29:47.000Z", 
                "started_at": "2020-10-07T18:29:47.000Z", 
                "conclusion": "success"
            }, 
            {
                "status": "completed", 
                "name": "Complete job", 
                "number": 19, 
                "completed_at": "2020-10-07T18:29:47.000Z", 
                "started_at": "2020-10-07T18:29:47.000Z", 
                "conclusion": "success"
            }
        ], 
        "head_sha": "abcb68288e4140d4b558bb7964f85bf78d45cb74", 
        "started_at": "2020-10-07T18:29:16Z", 
        "id": 1222121782, 
        "conclusion": "success"
    }, 
    {
        "status": "completed", 
        "check_run_url": "https://api.github.com/repos/rbsheth/hunter/check-runs/1222121801", 
        "name": "jpeg-compressor gcc-9-cxx17-fpic ubuntu-20.04", 
        "run_id": 293993383, 
        "url": "https://api.github.com/repos/rbsheth/hunter/actions/jobs/1222121801", 
        "html_url": "https://github.com/rbsheth/hunter/runs/1222121801", 
        "completed_at": "2020-10-07T18:29:53Z", 
        "run_url": "https://api.github.com/repos/rbsheth/hunter/actions/runs/293993383", 
        "node_id": "MDg6Q2hlY2tSdW4xMjIyMTIxODAx", 
        "steps": [
            {
                "status": "completed", 
                "name": "Set up job", 
                "number": 1, 
                "completed_at": "2020-10-07T18:29:14.000Z", 
                "started_at": "2020-10-07T18:29:11.000Z", 
                "conclusion": "success"
            }, 
            {
                "status": "completed", 
                "name": "Git checkout with submodules", 
                "number": 2, 
                "completed_at": "2020-10-07T18:29:22.000Z", 
                "started_at": "2020-10-07T18:29:14.000Z", 
                "conclusion": "success"
            }, 
            {
                "status": "completed", 
                "name": "Set up Python", 
                "number": 3, 
                "completed_at": "2020-10-07T18:29:22.000Z", 
                "started_at": "2020-10-07T18:29:22.000Z", 
                "conclusion": "success"
            }, 
            {
                "status": "completed", 
                "name": "Set up Python environment variable (Unix)", 
                "number": 4, 
                "completed_at": "2020-10-07T18:29:22.000Z", 
                "started_at": "2020-10-07T18:29:22.000Z", 
                "conclusion": "success"
            }, 
            {
                "status": "completed", 
                "name": "Set up Python environment variable (Windows)", 
                "number": 5, 
                "completed_at": "2020-10-07T18:29:22.000Z", 
                "started_at": "2020-10-07T18:29:22.000Z", 
                "conclusion": "skipped"
            }, 
            {
                "status": "completed", 
                "name": "Extract branch name", 
                "number": 6, 
                "completed_at": "2020-10-07T18:29:22.000Z", 
                "started_at": "2020-10-07T18:29:22.000Z", 
                "conclusion": "success"
            }, 
            {
                "status": "completed", 
                "name": "Upgrade pip", 
                "number": 7, 
                "completed_at": "2020-10-07T18:29:28.000Z", 
                "started_at": "2020-10-07T18:29:22.000Z", 
                "conclusion": "success"
            }, 
            {
                "status": "completed", 
                "name": "Build on Unix", 
                "number": 8, 
                "completed_at": "2020-10-07T18:29:53.000Z", 
                "started_at": "2020-10-07T18:29:28.000Z", 
                "conclusion": "success"
            }, 
            {
                "status": "completed", 
                "name": "Build on Windows", 
                "number": 9, 
                "completed_at": "2020-10-07T18:29:53.000Z", 
                "started_at": "2020-10-07T18:29:53.000Z", 
                "conclusion": "skipped"
            }, 
            {
                "status": "completed", 
                "name": "Post Git checkout with submodules", 
                "number": 18, 
                "completed_at": "2020-10-07T18:29:53.000Z", 
                "started_at": "2020-10-07T18:29:53.000Z", 
                "conclusion": "success"
            }, 
            {
                "status": "completed", 
                "name": "Complete job", 
                "number": 19, 
                "completed_at": "2020-10-07T18:29:53.000Z", 
                "started_at": "2020-10-07T18:29:53.000Z", 
                "conclusion": "success"
            }
        ], 
        "head_sha": "abcb68288e4140d4b558bb7964f85bf78d45cb74", 
        "started_at": "2020-10-07T18:29:11Z", 
        "id": 1222121801, 
        "conclusion": "success"
    }, 
    {
        "status": "completed", 
        "check_run_url": "https://api.github.com/repos/rbsheth/hunter/check-runs/1222121948", 
        "name": "jpeg-compressor ios-nocodesign-13-2-dep-9-3 macos-10.15", 
        "run_id": 293993383, 
        "url": "https://api.github.com/repos/rbsheth/hunter/actions/jobs/1222121948", 
        "html_url": "https://github.com/rbsheth/hunter/runs/1222121948", 
        "completed_at": "2020-10-07T18:46:54Z", 
        "run_url": "https://api.github.com/repos/rbsheth/hunter/actions/runs/293993383", 
        "node_id": "MDg6Q2hlY2tSdW4xMjIyMTIxOTQ4", 
        "steps": [
            {
                "status": "completed", 
                "name": "Set up job", 
                "number": 1, 
                "completed_at": "2020-10-07T18:44:40.000Z", 
                "started_at": "2020-10-07T18:44:38.000Z", 
                "conclusion": "success"
            }, 
            {
                "status": "completed", 
                "name": "Git checkout with submodules", 
                "number": 2, 
                "completed_at": "2020-10-07T18:44:46.000Z", 
                "started_at": "2020-10-07T18:44:40.000Z", 
                "conclusion": "success"
            }, 
            {
                "status": "completed", 
                "name": "Set up Python", 
                "number": 3, 
                "completed_at": "2020-10-07T18:44:46.000Z", 
                "started_at": "2020-10-07T18:44:46.000Z", 
                "conclusion": "success"
            }, 
            {
                "status": "completed", 
                "name": "Set up Python environment variable (Unix)", 
                "number": 4, 
                "completed_at": "2020-10-07T18:44:46.000Z", 
                "started_at": "2020-10-07T18:44:46.000Z", 
                "conclusion": "success"
            }, 
            {
                "status": "completed", 
                "name": "Set up Python environment variable (Windows)", 
                "number": 5, 
                "completed_at": "2020-10-07T18:44:46.000Z", 
                "started_at": "2020-10-07T18:44:46.000Z", 
                "conclusion": "skipped"
            }, 
            {
                "status": "completed", 
                "name": "Extract branch name", 
                "number": 6, 
                "completed_at": "2020-10-07T18:44:46.000Z", 
                "started_at": "2020-10-07T18:44:46.000Z", 
                "conclusion": "success"
            }, 
            {
                "status": "completed", 
                "name": "Upgrade pip", 
                "number": 7, 
                "completed_at": "2020-10-07T18:44:48.000Z", 
                "started_at": "2020-10-07T18:44:46.000Z", 
                "conclusion": "success"
            }, 
            {
                "status": "completed", 
                "name": "Build on Unix", 
                "number": 8, 
                "completed_at": "2020-10-07T18:46:53.000Z", 
                "started_at": "2020-10-07T18:44:48.000Z", 
                "conclusion": "success"
            }, 
            {
                "status": "completed", 
                "name": "Build on Windows", 
                "number": 9, 
                "completed_at": "2020-10-07T18:46:53.000Z", 
                "started_at": "2020-10-07T18:46:53.000Z", 
                "conclusion": "skipped"
            }, 
            {
                "status": "completed", 
                "name": "Post Git checkout with submodules", 
                "number": 18, 
                "completed_at": "2020-10-07T18:46:54.000Z", 
                "started_at": "2020-10-07T18:46:53.000Z", 
                "conclusion": "success"
            }, 
            {
                "status": "completed", 
                "name": "Complete job", 
                "number": 19, 
                "completed_at": "2020-10-07T18:46:54.000Z", 
                "started_at": "2020-10-07T18:46:54.000Z", 
                "conclusion": "success"
            }
        ], 
        "head_sha": "abcb68288e4140d4b558bb7964f85bf78d45cb74", 
        "started_at": "2020-10-07T18:44:38Z", 
        "id": 1222121948, 
        "conclusion": "success"
    }, 
    {
        "status": "completed", 
        "check_run_url": "https://api.github.com/repos/rbsheth/hunter/check-runs/1222122027", 
        "name": "jpeg-compressor mingw-cxx17 windows-2016", 
        "run_id": 293993383, 
        "url": "https://api.github.com/repos/rbsheth/hunter/actions/jobs/1222122027", 
        "html_url": "https://github.com/rbsheth/hunter/runs/1222122027", 
        "completed_at": "2020-10-07T18:33:03Z", 
        "run_url": "https://api.github.com/repos/rbsheth/hunter/actions/runs/293993383", 
        "node_id": "MDg6Q2hlY2tSdW4xMjIyMTIyMDI3", 
        "steps": [
            {
                "status": "completed", 
                "name": "Set up job", 
                "number": 1, 
                "completed_at": "2020-10-07T18:31:35.000Z", 
                "started_at": "2020-10-07T18:31:32.000Z", 
                "conclusion": "success"
            }, 
            {
                "status": "completed", 
                "name": "Git checkout with submodules", 
                "number": 2, 
                "completed_at": "2020-10-07T18:31:51.000Z", 
                "started_at": "2020-10-07T18:31:35.000Z", 
                "conclusion": "success"
            }, 
            {
                "status": "completed", 
                "name": "Set up Python", 
                "number": 3, 
                "completed_at": "2020-10-07T18:31:52.000Z", 
                "started_at": "2020-10-07T18:31:51.000Z", 
                "conclusion": "success"
            }, 
            {
                "status": "completed", 
                "name": "Set up Python environment variable (Unix)", 
                "number": 4, 
                "completed_at": "2020-10-07T18:31:52.000Z", 
                "started_at": "2020-10-07T18:31:52.000Z", 
                "conclusion": "skipped"
            }, 
            {
                "status": "completed", 
                "name": "Set up Python environment variable (Windows)", 
                "number": 5, 
                "completed_at": "2020-10-07T18:32:00.000Z", 
                "started_at": "2020-10-07T18:31:52.000Z", 
                "conclusion": "success"
            }, 
            {
                "status": "completed", 
                "name": "Extract branch name", 
                "number": 6, 
                "completed_at": "2020-10-07T18:32:01.000Z", 
                "started_at": "2020-10-07T18:32:00.000Z", 
                "conclusion": "success"
            }, 
            {
                "status": "completed", 
                "name": "Upgrade pip", 
                "number": 7, 
                "completed_at": "2020-10-07T18:32:08.000Z", 
                "started_at": "2020-10-07T18:32:01.000Z", 
                "conclusion": "success"
            }, 
            {
                "status": "completed", 
                "name": "Build on Unix", 
                "number": 8, 
                "completed_at": "2020-10-07T18:32:08.000Z", 
                "started_at": "2020-10-07T18:32:08.000Z", 
                "conclusion": "skipped"
            }, 
            {
                "status": "completed", 
                "name": "Build on Windows", 
                "number": 9, 
                "completed_at": "2020-10-07T18:33:00.000Z", 
                "started_at": "2020-10-07T18:32:08.000Z", 
                "conclusion": "success"
            }, 
            {
                "status": "completed", 
                "name": "Post Git checkout with submodules", 
                "number": 18, 
                "completed_at": "2020-10-07T18:33:03.000Z", 
                "started_at": "2020-10-07T18:33:00.000Z", 
                "conclusion": "success"
            }, 
            {
                "status": "completed", 
                "name": "Complete job", 
                "number": 19, 
                "completed_at": "2020-10-07T18:33:03.000Z", 
                "started_at": "2020-10-07T18:33:03.000Z", 
                "conclusion": "success"
            }
        ], 
        "head_sha": "abcb68288e4140d4b558bb7964f85bf78d45cb74", 
        "started_at": "2020-10-07T18:31:32Z", 
        "id": 1222122027, 
        "conclusion": "success"
    }, 
    {
        "status": "completed", 
        "check_run_url": "https://api.github.com/repos/rbsheth/hunter/check-runs/1222122041", 
        "name": "jpeg-compressor msys-cxx17 windows-2016", 
        "run_id": 293993383, 
        "url": "https://api.github.com/repos/rbsheth/hunter/actions/jobs/1222122041", 
        "html_url": "https://github.com/rbsheth/hunter/runs/1222122041", 
        "completed_at": "2020-10-07T18:34:08Z", 
        "run_url": "https://api.github.com/repos/rbsheth/hunter/actions/runs/293993383", 
        "node_id": "MDg6Q2hlY2tSdW4xMjIyMTIyMDQx", 
        "steps": [
            {
                "status": "completed", 
                "name": "Set up job", 
                "number": 1, 
                "completed_at": "2020-10-07T18:31:34.000Z", 
                "started_at": "2020-10-07T18:31:32.000Z", 
                "conclusion": "success"
            }, 
            {
                "status": "completed", 
                "name": "Git checkout with submodules", 
                "number": 2, 
                "completed_at": "2020-10-07T18:31:49.000Z", 
                "started_at": "2020-10-07T18:31:34.000Z", 
                "conclusion": "success"
            }, 
            {
                "status": "completed", 
                "name": "Set up Python", 
                "number": 3, 
                "completed_at": "2020-10-07T18:31:50.000Z", 
                "started_at": "2020-10-07T18:31:49.000Z", 
                "conclusion": "success"
            }, 
            {
                "status": "completed", 
                "name": "Set up Python environment variable (Unix)", 
                "number": 4, 
                "completed_at": "2020-10-07T18:31:50.000Z", 
                "started_at": "2020-10-07T18:31:50.000Z", 
                "conclusion": "skipped"
            }, 
            {
                "status": "completed", 
                "name": "Set up Python environment variable (Windows)", 
                "number": 5, 
                "completed_at": "2020-10-07T18:31:57.000Z", 
                "started_at": "2020-10-07T18:31:50.000Z", 
                "conclusion": "success"
            }, 
            {
                "status": "completed", 
                "name": "Extract branch name", 
                "number": 6, 
                "completed_at": "2020-10-07T18:31:57.000Z", 
                "started_at": "2020-10-07T18:31:57.000Z", 
                "conclusion": "success"
            }, 
            {
                "status": "completed", 
                "name": "Upgrade pip", 
                "number": 7, 
                "completed_at": "2020-10-07T18:32:04.000Z", 
                "started_at": "2020-10-07T18:31:57.000Z", 
                "conclusion": "success"
            }, 
            {
                "status": "completed", 
                "name": "Build on Unix", 
                "number": 8, 
                "completed_at": "2020-10-07T18:32:04.000Z", 
                "started_at": "2020-10-07T18:32:04.000Z", 
                "conclusion": "skipped"
            }, 
            {
                "status": "completed", 
                "name": "Build on Windows", 
                "number": 9, 
                "completed_at": "2020-10-07T18:34:05.000Z", 
                "started_at": "2020-10-07T18:32:04.000Z", 
                "conclusion": "success"
            }, 
            {
                "status": "completed", 
                "name": "Post Git checkout with submodules", 
                "number": 18, 
                "completed_at": "2020-10-07T18:34:08.000Z", 
                "started_at": "2020-10-07T18:34:05.000Z", 
                "conclusion": "success"
            }, 
            {
                "status": "completed", 
                "name": "Complete job", 
                "number": 19, 
                "completed_at": "2020-10-07T18:34:08.000Z", 
                "started_at": "2020-10-07T18:34:08.000Z", 
                "conclusion": "success"
            }
        ], 
        "head_sha": "abcb68288e4140d4b558bb7964f85bf78d45cb74", 
        "started_at": "2020-10-07T18:31:32Z", 
        "id": 1222122041, 
        "conclusion": "success"
    }, 
    {
        "status": "completed", 
        "check_run_url": "https://api.github.com/repos/rbsheth/hunter/check-runs/1222121979", 
        "name": "jpeg-compressor ninja-vs-15-2017-win64-cxx17 windows-2016", 
        "run_id": 293993383, 
        "url": "https://api.github.com/repos/rbsheth/hunter/actions/jobs/1222121979", 
        "html_url": "https://github.com/rbsheth/hunter/runs/1222121979", 
        "completed_at": "2020-10-07T18:33:05Z", 
        "run_url": "https://api.github.com/repos/rbsheth/hunter/actions/runs/293993383", 
        "node_id": "MDg6Q2hlY2tSdW4xMjIyMTIxOTc5", 
        "steps": [
            {
                "status": "completed", 
                "name": "Set up job", 
                "number": 1, 
                "completed_at": "2020-10-07T18:31:34.000Z", 
                "started_at": "2020-10-07T18:31:33.000Z", 
                "conclusion": "success"
            }, 
            {
                "status": "completed", 
                "name": "Git checkout with submodules", 
                "number": 2, 
                "completed_at": "2020-10-07T18:31:51.000Z", 
                "started_at": "2020-10-07T18:31:34.000Z", 
                "conclusion": "success"
            }, 
            {
                "status": "completed", 
                "name": "Set up Python", 
                "number": 3, 
                "completed_at": "2020-10-07T18:31:52.000Z", 
                "started_at": "2020-10-07T18:31:51.000Z", 
                "conclusion": "success"
            }, 
            {
                "status": "completed", 
                "name": "Set up Python environment variable (Unix)", 
                "number": 4, 
                "completed_at": "2020-10-07T18:31:52.000Z", 
                "started_at": "2020-10-07T18:31:52.000Z", 
                "conclusion": "skipped"
            }, 
            {
                "status": "completed", 
                "name": "Set up Python environment variable (Windows)", 
                "number": 5, 
                "completed_at": "2020-10-07T18:32:01.000Z", 
                "started_at": "2020-10-07T18:31:52.000Z", 
                "conclusion": "success"
            }, 
            {
                "status": "completed", 
                "name": "Extract branch name", 
                "number": 6, 
                "completed_at": "2020-10-07T18:32:01.000Z", 
                "started_at": "2020-10-07T18:32:01.000Z", 
                "conclusion": "success"
            }, 
            {
                "status": "completed", 
                "name": "Upgrade pip", 
                "number": 7, 
                "completed_at": "2020-10-07T18:32:08.000Z", 
                "started_at": "2020-10-07T18:32:01.000Z", 
                "conclusion": "success"
            }, 
            {
                "status": "completed", 
                "name": "Build on Unix", 
                "number": 8, 
                "completed_at": "2020-10-07T18:32:08.000Z", 
                "started_at": "2020-10-07T18:32:08.000Z", 
                "conclusion": "skipped"
            }, 
            {
                "status": "completed", 
                "name": "Build on Windows", 
                "number": 9, 
                "completed_at": "2020-10-07T18:33:01.000Z", 
                "started_at": "2020-10-07T18:32:08.000Z", 
                "conclusion": "success"
            }, 
            {
                "status": "completed", 
                "name": "Post Git checkout with submodules", 
                "number": 18, 
                "completed_at": "2020-10-07T18:33:05.000Z", 
                "started_at": "2020-10-07T18:33:01.000Z", 
                "conclusion": "success"
            }, 
            {
                "status": "completed", 
                "name": "Complete job", 
                "number": 19, 
                "completed_at": "2020-10-07T18:33:05.000Z", 
                "started_at": "2020-10-07T18:33:05.000Z", 
                "conclusion": "success"
            }
        ], 
        "head_sha": "abcb68288e4140d4b558bb7964f85bf78d45cb74", 
        "started_at": "2020-10-07T18:31:33Z", 
        "id": 1222121979, 
        "conclusion": "success"
    }, 
    {
        "status": "completed", 
        "check_run_url": "https://api.github.com/repos/rbsheth/hunter/check-runs/1222121985", 
        "name": "jpeg-compressor nmake-vs-15-2017-win64-cxx17 windows-2016", 
        "run_id": 293993383, 
        "url": "https://api.github.com/repos/rbsheth/hunter/actions/jobs/1222121985", 
        "html_url": "https://github.com/rbsheth/hunter/runs/1222121985", 
        "completed_at": "2020-10-07T18:32:51Z", 
        "run_url": "https://api.github.com/repos/rbsheth/hunter/actions/runs/293993383", 
        "node_id": "MDg6Q2hlY2tSdW4xMjIyMTIxOTg1", 
        "steps": [
            {
                "status": "completed", 
                "name": "Set up job", 
                "number": 1, 
                "completed_at": "2020-10-07T18:31:35.000Z", 
                "started_at": "2020-10-07T18:31:33.000Z", 
                "conclusion": "success"
            }, 
            {
                "status": "completed", 
                "name": "Git checkout with submodules", 
                "number": 2, 
                "completed_at": "2020-10-07T18:31:48.000Z", 
                "started_at": "2020-10-07T18:31:35.000Z", 
                "conclusion": "success"
            }, 
            {
                "status": "completed", 
                "name": "Set up Python", 
                "number": 3, 
                "completed_at": "2020-10-07T18:31:48.000Z", 
                "started_at": "2020-10-07T18:31:48.000Z", 
                "conclusion": "success"
            }, 
            {
                "status": "completed", 
                "name": "Set up Python environment variable (Unix)", 
                "number": 4, 
                "completed_at": "2020-10-07T18:31:48.000Z", 
                "started_at": "2020-10-07T18:31:48.000Z", 
                "conclusion": "skipped"
            }, 
            {
                "status": "completed", 
                "name": "Set up Python environment variable (Windows)", 
                "number": 5, 
                "completed_at": "2020-10-07T18:31:56.000Z", 
                "started_at": "2020-10-07T18:31:48.000Z", 
                "conclusion": "success"
            }, 
            {
                "status": "completed", 
                "name": "Extract branch name", 
                "number": 6, 
                "completed_at": "2020-10-07T18:31:56.000Z", 
                "started_at": "2020-10-07T18:31:56.000Z", 
                "conclusion": "success"
            }, 
            {
                "status": "completed", 
                "name": "Upgrade pip", 
                "number": 7, 
                "completed_at": "2020-10-07T18:32:02.000Z", 
                "started_at": "2020-10-07T18:31:56.000Z", 
                "conclusion": "success"
            }, 
            {
                "status": "completed", 
                "name": "Build on Unix", 
                "number": 8, 
                "completed_at": "2020-10-07T18:32:02.000Z", 
                "started_at": "2020-10-07T18:32:02.000Z", 
                "conclusion": "skipped"
            }, 
            {
                "status": "completed", 
                "name": "Build on Windows", 
                "number": 9, 
                "completed_at": "2020-10-07T18:32:48.000Z", 
                "started_at": "2020-10-07T18:32:02.000Z", 
                "conclusion": "success"
            }, 
            {
                "status": "completed", 
                "name": "Post Git checkout with submodules", 
                "number": 18, 
                "completed_at": "2020-10-07T18:32:51.000Z", 
                "started_at": "2020-10-07T18:32:48.000Z", 
                "conclusion": "success"
            }, 
            {
                "status": "completed", 
                "name": "Complete job", 
                "number": 19, 
                "completed_at": "2020-10-07T18:32:51.000Z", 
                "started_at": "2020-10-07T18:32:51.000Z", 
                "conclusion": "success"
            }
        ], 
        "head_sha": "abcb68288e4140d4b558bb7964f85bf78d45cb74", 
        "started_at": "2020-10-07T18:31:33Z", 
        "id": 1222121985, 
        "conclusion": "success"
    }, 
    {
        "status": "completed", 
        "check_run_url": "https://api.github.com/repos/rbsheth/hunter/check-runs/1222121910", 
        "name": "jpeg-compressor osx-10-13-cxx14 macos-10.15", 
        "run_id": 293993383, 
        "url": "https://api.github.com/repos/rbsheth/hunter/actions/jobs/1222121910", 
        "html_url": "https://github.com/rbsheth/hunter/runs/1222121910", 
        "completed_at": "2020-10-07T18:46:53Z", 
        "run_url": "https://api.github.com/repos/rbsheth/hunter/actions/runs/293993383", 
        "node_id": "MDg6Q2hlY2tSdW4xMjIyMTIxOTEw", 
        "steps": [
            {
                "status": "completed", 
                "name": "Set up job", 
                "number": 1, 
                "completed_at": "2020-10-07T18:45:10.000Z", 
                "started_at": "2020-10-07T18:45:09.000Z", 
                "conclusion": "success"
            }, 
            {
                "status": "completed", 
                "name": "Git checkout with submodules", 
                "number": 2, 
                "completed_at": "2020-10-07T18:45:17.000Z", 
                "started_at": "2020-10-07T18:45:10.000Z", 
                "conclusion": "success"
            }, 
            {
                "status": "completed", 
                "name": "Set up Python", 
                "number": 3, 
                "completed_at": "2020-10-07T18:45:17.000Z", 
                "started_at": "2020-10-07T18:45:17.000Z", 
                "conclusion": "success"
            }, 
            {
                "status": "completed", 
                "name": "Set up Python environment variable (Unix)", 
                "number": 4, 
                "completed_at": "2020-10-07T18:45:17.000Z", 
                "started_at": "2020-10-07T18:45:17.000Z", 
                "conclusion": "success"
            }, 
            {
                "status": "completed", 
                "name": "Set up Python environment variable (Windows)", 
                "number": 5, 
                "completed_at": "2020-10-07T18:45:17.000Z", 
                "started_at": "2020-10-07T18:45:17.000Z", 
                "conclusion": "skipped"
            }, 
            {
                "status": "completed", 
                "name": "Extract branch name", 
                "number": 6, 
                "completed_at": "2020-10-07T18:45:17.000Z", 
                "started_at": "2020-10-07T18:45:17.000Z", 
                "conclusion": "success"
            }, 
            {
                "status": "completed", 
                "name": "Upgrade pip", 
                "number": 7, 
                "completed_at": "2020-10-07T18:45:19.000Z", 
                "started_at": "2020-10-07T18:45:17.000Z", 
                "conclusion": "success"
            }, 
            {
                "status": "completed", 
                "name": "Build on Unix", 
                "number": 8, 
                "completed_at": "2020-10-07T18:46:52.000Z", 
                "started_at": "2020-10-07T18:45:19.000Z", 
                "conclusion": "success"
            }, 
            {
                "status": "completed", 
                "name": "Build on Windows", 
                "number": 9, 
                "completed_at": "2020-10-07T18:46:52.000Z", 
                "started_at": "2020-10-07T18:46:52.000Z", 
                "conclusion": "skipped"
            }, 
            {
                "status": "completed", 
                "name": "Post Git checkout with submodules", 
                "number": 18, 
                "completed_at": "2020-10-07T18:46:53.000Z", 
                "started_at": "2020-10-07T18:46:52.000Z", 
                "conclusion": "success"
            }, 
            {
                "status": "completed", 
                "name": "Complete job", 
                "number": 19, 
                "completed_at": "2020-10-07T18:46:53.000Z", 
                "started_at": "2020-10-07T18:46:53.000Z", 
                "conclusion": "success"
            }
        ], 
        "head_sha": "abcb68288e4140d4b558bb7964f85bf78d45cb74", 
        "started_at": "2020-10-07T18:45:08Z", 
        "id": 1222121910, 
        "conclusion": "success"
    }, 
    {
        "status": "completed", 
        "check_run_url": "https://api.github.com/repos/rbsheth/hunter/check-runs/1222121892", 
        "name": "jpeg-compressor osx-10-13-make-cxx14 macos-10.15", 
        "run_id": 293993383, 
        "url": "https://api.github.com/repos/rbsheth/hunter/actions/jobs/1222121892", 
        "html_url": "https://github.com/rbsheth/hunter/runs/1222121892", 
        "completed_at": "2020-10-07T18:45:55Z", 
        "run_url": "https://api.github.com/repos/rbsheth/hunter/actions/runs/293993383", 
        "node_id": "MDg6Q2hlY2tSdW4xMjIyMTIxODky", 
        "steps": [
            {
                "status": "completed", 
                "name": "Set up job", 
                "number": 1, 
                "completed_at": "2020-10-07T18:45:12.000Z", 
                "started_at": "2020-10-07T18:45:10.000Z", 
                "conclusion": "success"
            }, 
            {
                "status": "completed", 
                "name": "Git checkout with submodules", 
                "number": 2, 
                "completed_at": "2020-10-07T18:45:19.000Z", 
                "started_at": "2020-10-07T18:45:12.000Z", 
                "conclusion": "success"
            }, 
            {
                "status": "completed", 
                "name": "Set up Python", 
                "number": 3, 
                "completed_at": "2020-10-07T18:45:19.000Z", 
                "started_at": "2020-10-07T18:45:19.000Z", 
                "conclusion": "success"
            }, 
            {
                "status": "completed", 
                "name": "Set up Python environment variable (Unix)", 
                "number": 4, 
                "completed_at": "2020-10-07T18:45:19.000Z", 
                "started_at": "2020-10-07T18:45:19.000Z", 
                "conclusion": "success"
            }, 
            {
                "status": "completed", 
                "name": "Set up Python environment variable (Windows)", 
                "number": 5, 
                "completed_at": "2020-10-07T18:45:19.000Z", 
                "started_at": "2020-10-07T18:45:19.000Z", 
                "conclusion": "skipped"
            }, 
            {
                "status": "completed", 
                "name": "Extract branch name", 
                "number": 6, 
                "completed_at": "2020-10-07T18:45:19.000Z", 
                "started_at": "2020-10-07T18:45:19.000Z", 
                "conclusion": "success"
            }, 
            {
                "status": "completed", 
                "name": "Upgrade pip", 
                "number": 7, 
                "completed_at": "2020-10-07T18:45:21.000Z", 
                "started_at": "2020-10-07T18:45:19.000Z", 
                "conclusion": "success"
            }, 
            {
                "status": "completed", 
                "name": "Build on Unix", 
                "number": 8, 
                "completed_at": "2020-10-07T18:45:55.000Z", 
                "started_at": "2020-10-07T18:45:21.000Z", 
                "conclusion": "success"
            }, 
            {
                "status": "completed", 
                "name": "Build on Windows", 
                "number": 9, 
                "completed_at": "2020-10-07T18:45:55.000Z", 
                "started_at": "2020-10-07T18:45:55.000Z", 
                "conclusion": "skipped"
            }, 
            {
                "status": "completed", 
                "name": "Post Git checkout with submodules", 
                "number": 18, 
                "completed_at": "2020-10-07T18:45:55.000Z", 
                "started_at": "2020-10-07T18:45:55.000Z", 
                "conclusion": "success"
            }, 
            {
                "status": "completed", 
                "name": "Complete job", 
                "number": 19, 
                "completed_at": "2020-10-07T18:45:55.000Z", 
                "started_at": "2020-10-07T18:45:55.000Z", 
                "conclusion": "success"
            }
        ], 
        "head_sha": "abcb68288e4140d4b558bb7964f85bf78d45cb74", 
        "started_at": "2020-10-07T18:45:10Z", 
        "id": 1222121892, 
        "conclusion": "success"
    }, 
    {
        "status": "completed", 
        "check_run_url": "https://api.github.com/repos/rbsheth/hunter/check-runs/1222121925", 
        "name": "jpeg-compressor osx-10-15-dep-10-10-cxx17 macos-10.15", 
        "run_id": 293993383, 
        "url": "https://api.github.com/repos/rbsheth/hunter/actions/jobs/1222121925", 
        "html_url": "https://github.com/rbsheth/hunter/runs/1222121925", 
        "completed_at": "2020-10-07T18:46:15Z", 
        "run_url": "https://api.github.com/repos/rbsheth/hunter/actions/runs/293993383", 
        "node_id": "MDg6Q2hlY2tSdW4xMjIyMTIxOTI1", 
        "steps": [
            {
                "status": "completed", 
                "name": "Set up job", 
                "number": 1, 
                "completed_at": "2020-10-07T18:44:39.000Z", 
                "started_at": "2020-10-07T18:44:38.000Z", 
                "conclusion": "success"
            }, 
            {
                "status": "completed", 
                "name": "Git checkout with submodules", 
                "number": 2, 
                "completed_at": "2020-10-07T18:44:46.000Z", 
                "started_at": "2020-10-07T18:44:39.000Z", 
                "conclusion": "success"
            }, 
            {
                "status": "completed", 
                "name": "Set up Python", 
                "number": 3, 
                "completed_at": "2020-10-07T18:44:46.000Z", 
                "started_at": "2020-10-07T18:44:46.000Z", 
                "conclusion": "success"
            }, 
            {
                "status": "completed", 
                "name": "Set up Python environment variable (Unix)", 
                "number": 4, 
                "completed_at": "2020-10-07T18:44:46.000Z", 
                "started_at": "2020-10-07T18:44:46.000Z", 
                "conclusion": "success"
            }, 
            {
                "status": "completed", 
                "name": "Set up Python environment variable (Windows)", 
                "number": 5, 
                "completed_at": "2020-10-07T18:44:46.000Z", 
                "started_at": "2020-10-07T18:44:46.000Z", 
                "conclusion": "skipped"
            }, 
            {
                "status": "completed", 
                "name": "Extract branch name", 
                "number": 6, 
                "completed_at": "2020-10-07T18:44:46.000Z", 
                "started_at": "2020-10-07T18:44:46.000Z", 
                "conclusion": "success"
            }, 
            {
                "status": "completed", 
                "name": "Upgrade pip", 
                "number": 7, 
                "completed_at": "2020-10-07T18:44:48.000Z", 
                "started_at": "2020-10-07T18:44:46.000Z", 
                "conclusion": "success"
            }, 
            {
                "status": "completed", 
                "name": "Build on Unix", 
                "number": 8, 
                "completed_at": "2020-10-07T18:46:14.000Z", 
                "started_at": "2020-10-07T18:44:48.000Z", 
                "conclusion": "success"
            }, 
            {
                "status": "completed", 
                "name": "Build on Windows", 
                "number": 9, 
                "completed_at": "2020-10-07T18:46:14.000Z", 
                "started_at": "2020-10-07T18:46:14.000Z", 
                "conclusion": "skipped"
            }, 
            {
                "status": "completed", 
                "name": "Post Git checkout with submodules", 
                "number": 18, 
                "completed_at": "2020-10-07T18:46:15.000Z", 
                "started_at": "2020-10-07T18:46:14.000Z", 
                "conclusion": "success"
            }, 
            {
                "status": "completed", 
                "name": "Complete job", 
                "number": 19, 
                "completed_at": "2020-10-07T18:46:15.000Z", 
                "started_at": "2020-10-07T18:46:15.000Z", 
                "conclusion": "success"
            }
        ], 
        "head_sha": "abcb68288e4140d4b558bb7964f85bf78d45cb74", 
        "started_at": "2020-10-07T18:44:38Z", 
        "id": 1222121925, 
        "conclusion": "success"
    }, 
    {
        "status": "completed", 
        "check_run_url": "https://api.github.com/repos/rbsheth/hunter/check-runs/1222121840", 
        "name": "jpeg-compressor sanitize-address-cxx17 ubuntu-16.04", 
        "run_id": 293993383, 
        "url": "https://api.github.com/repos/rbsheth/hunter/actions/jobs/1222121840", 
        "html_url": "https://github.com/rbsheth/hunter/runs/1222121840", 
        "completed_at": "2020-10-07T18:30:00Z", 
        "run_url": "https://api.github.com/repos/rbsheth/hunter/actions/runs/293993383", 
        "node_id": "MDg6Q2hlY2tSdW4xMjIyMTIxODQw", 
        "steps": [
            {
                "status": "completed", 
                "name": "Set up job", 
                "number": 1, 
                "completed_at": "2020-10-07T18:29:22.000Z", 
                "started_at": "2020-10-07T18:29:19.000Z", 
                "conclusion": "success"
            }, 
            {
                "status": "completed", 
                "name": "Git checkout with submodules", 
                "number": 2, 
                "completed_at": "2020-10-07T18:29:28.000Z", 
                "started_at": "2020-10-07T18:29:22.000Z", 
                "conclusion": "success"
            }, 
            {
                "status": "completed", 
                "name": "Set up Python", 
                "number": 3, 
                "completed_at": "2020-10-07T18:29:28.000Z", 
                "started_at": "2020-10-07T18:29:28.000Z", 
                "conclusion": "success"
            }, 
            {
                "status": "completed", 
                "name": "Set up Python environment variable (Unix)", 
                "number": 4, 
                "completed_at": "2020-10-07T18:29:28.000Z", 
                "started_at": "2020-10-07T18:29:28.000Z", 
                "conclusion": "success"
            }, 
            {
                "status": "completed", 
                "name": "Set up Python environment variable (Windows)", 
                "number": 5, 
                "completed_at": "2020-10-07T18:29:28.000Z", 
                "started_at": "2020-10-07T18:29:28.000Z", 
                "conclusion": "skipped"
            }, 
            {
                "status": "completed", 
                "name": "Extract branch name", 
                "number": 6, 
                "completed_at": "2020-10-07T18:29:28.000Z", 
                "started_at": "2020-10-07T18:29:28.000Z", 
                "conclusion": "success"
            }, 
            {
                "status": "completed", 
                "name": "Upgrade pip", 
                "number": 7, 
                "completed_at": "2020-10-07T18:29:32.000Z", 
                "started_at": "2020-10-07T18:29:28.000Z", 
                "conclusion": "success"
            }, 
            {
                "status": "completed", 
                "name": "Build on Unix", 
                "number": 8, 
                "completed_at": "2020-10-07T18:30:00.000Z", 
                "started_at": "2020-10-07T18:29:32.000Z", 
                "conclusion": "success"
            }, 
            {
                "status": "completed", 
                "name": "Build on Windows", 
                "number": 9, 
                "completed_at": "2020-10-07T18:30:00.000Z", 
                "started_at": "2020-10-07T18:30:00.000Z", 
                "conclusion": "skipped"
            }, 
            {
                "status": "completed", 
                "name": "Post Git checkout with submodules", 
                "number": 18, 
                "completed_at": "2020-10-07T18:30:00.000Z", 
                "started_at": "2020-10-07T18:30:00.000Z", 
                "conclusion": "success"
            }, 
            {
                "status": "completed", 
                "name": "Complete job", 
                "number": 19, 
                "completed_at": "2020-10-07T18:30:00.000Z", 
                "started_at": "2020-10-07T18:30:00.000Z", 
                "conclusion": "success"
            }
        ], 
        "head_sha": "abcb68288e4140d4b558bb7964f85bf78d45cb74", 
        "started_at": "2020-10-07T18:29:19Z", 
        "id": 1222121840, 
        "conclusion": "success"
    }, 
    {
        "status": "completed", 
        "check_run_url": "https://api.github.com/repos/rbsheth/hunter/check-runs/1222121861", 
        "name": "jpeg-compressor sanitize-leak-cxx17 ubuntu-16.04", 
        "run_id": 293993383, 
        "url": "https://api.github.com/repos/rbsheth/hunter/actions/jobs/1222121861", 
        "html_url": "https://github.com/rbsheth/hunter/runs/1222121861", 
        "completed_at": "2020-10-07T18:31:44Z", 
        "run_url": "https://api.github.com/repos/rbsheth/hunter/actions/runs/293993383", 
        "node_id": "MDg6Q2hlY2tSdW4xMjIyMTIxODYx", 
        "steps": [
            {
                "status": "completed", 
                "name": "Set up job", 
                "number": 1, 
                "completed_at": "2020-10-07T18:31:09.000Z", 
                "started_at": "2020-10-07T18:31:05.000Z", 
                "conclusion": "success"
            }, 
            {
                "status": "completed", 
                "name": "Git checkout with submodules", 
                "number": 2, 
                "completed_at": "2020-10-07T18:31:18.000Z", 
                "started_at": "2020-10-07T18:31:09.000Z", 
                "conclusion": "success"
            }, 
            {
                "status": "completed", 
                "name": "Set up Python", 
                "number": 3, 
                "completed_at": "2020-10-07T18:31:18.000Z", 
                "started_at": "2020-10-07T18:31:18.000Z", 
                "conclusion": "success"
            }, 
            {
                "status": "completed", 
                "name": "Set up Python environment variable (Unix)", 
                "number": 4, 
                "completed_at": "2020-10-07T18:31:18.000Z", 
                "started_at": "2020-10-07T18:31:18.000Z", 
                "conclusion": "success"
            }, 
            {
                "status": "completed", 
                "name": "Set up Python environment variable (Windows)", 
                "number": 5, 
                "completed_at": "2020-10-07T18:31:18.000Z", 
                "started_at": "2020-10-07T18:31:18.000Z", 
                "conclusion": "skipped"
            }, 
            {
                "status": "completed", 
                "name": "Extract branch name", 
                "number": 6, 
                "completed_at": "2020-10-07T18:31:18.000Z", 
                "started_at": "2020-10-07T18:31:18.000Z", 
                "conclusion": "success"
            }, 
            {
                "status": "completed", 
                "name": "Upgrade pip", 
                "number": 7, 
                "completed_at": "2020-10-07T18:31:20.000Z", 
                "started_at": "2020-10-07T18:31:18.000Z", 
                "conclusion": "success"
            }, 
            {
                "status": "completed", 
                "name": "Build on Unix", 
                "number": 8, 
                "completed_at": "2020-10-07T18:31:43.000Z", 
                "started_at": "2020-10-07T18:31:20.000Z", 
                "conclusion": "success"
            }, 
            {
                "status": "completed", 
                "name": "Build on Windows", 
                "number": 9, 
                "completed_at": "2020-10-07T18:31:43.000Z", 
                "started_at": "2020-10-07T18:31:43.000Z", 
                "conclusion": "skipped"
            }, 
            {
                "status": "completed", 
                "name": "Post Git checkout with submodules", 
                "number": 18, 
                "completed_at": "2020-10-07T18:31:44.000Z", 
                "started_at": "2020-10-07T18:31:43.000Z", 
                "conclusion": "success"
            }, 
            {
                "status": "completed", 
                "name": "Complete job", 
                "number": 19, 
                "completed_at": "2020-10-07T18:31:44.000Z", 
                "started_at": "2020-10-07T18:31:44.000Z", 
                "conclusion": "success"
            }
        ], 
        "head_sha": "abcb68288e4140d4b558bb7964f85bf78d45cb74", 
        "started_at": "2020-10-07T18:31:05Z", 
        "id": 1222121861, 
        "conclusion": "success"
    }, 
    {
        "status": "completed", 
        "check_run_url": "https://api.github.com/repos/rbsheth/hunter/check-runs/1222121874", 
        "name": "jpeg-compressor sanitize-thread-cxx17 ubuntu-16.04", 
        "run_id": 293993383, 
        "url": "https://api.github.com/repos/rbsheth/hunter/actions/jobs/1222121874", 
        "html_url": "https://github.com/rbsheth/hunter/runs/1222121874", 
        "completed_at": "2020-10-07T18:30:10Z", 
        "run_url": "https://api.github.com/repos/rbsheth/hunter/actions/runs/293993383", 
        "node_id": "MDg6Q2hlY2tSdW4xMjIyMTIxODc0", 
        "steps": [
            {
                "status": "completed", 
                "name": "Set up job", 
                "number": 1, 
                "completed_at": "2020-10-07T18:29:24.000Z", 
                "started_at": "2020-10-07T18:29:20.000Z", 
                "conclusion": "success"
            }, 
            {
                "status": "completed", 
                "name": "Git checkout with submodules", 
                "number": 2, 
                "completed_at": "2020-10-07T18:29:32.000Z", 
                "started_at": "2020-10-07T18:29:24.000Z", 
                "conclusion": "success"
            }, 
            {
                "status": "completed", 
                "name": "Set up Python", 
                "number": 3, 
                "completed_at": "2020-10-07T18:29:32.000Z", 
                "started_at": "2020-10-07T18:29:32.000Z", 
                "conclusion": "success"
            }, 
            {
                "status": "completed", 
                "name": "Set up Python environment variable (Unix)", 
                "number": 4, 
                "completed_at": "2020-10-07T18:29:32.000Z", 
                "started_at": "2020-10-07T18:29:32.000Z", 
                "conclusion": "success"
            }, 
            {
                "status": "completed", 
                "name": "Set up Python environment variable (Windows)", 
                "number": 5, 
                "completed_at": "2020-10-07T18:29:32.000Z", 
                "started_at": "2020-10-07T18:29:32.000Z", 
                "conclusion": "skipped"
            }, 
            {
                "status": "completed", 
                "name": "Extract branch name", 
                "number": 6, 
                "completed_at": "2020-10-07T18:29:32.000Z", 
                "started_at": "2020-10-07T18:29:32.000Z", 
                "conclusion": "success"
            }, 
            {
                "status": "completed", 
                "name": "Upgrade pip", 
                "number": 7, 
                "completed_at": "2020-10-07T18:29:36.000Z", 
                "started_at": "2020-10-07T18:29:32.000Z", 
                "conclusion": "success"
            }, 
            {
                "status": "completed", 
                "name": "Build on Unix", 
                "number": 8, 
                "completed_at": "2020-10-07T18:30:10.000Z", 
                "started_at": "2020-10-07T18:29:36.000Z", 
                "conclusion": "success"
            }, 
            {
                "status": "completed", 
                "name": "Build on Windows", 
                "number": 9, 
                "completed_at": "2020-10-07T18:30:10.000Z", 
                "started_at": "2020-10-07T18:30:10.000Z", 
                "conclusion": "skipped"
            }, 
            {
                "status": "completed", 
                "name": "Post Git checkout with submodules", 
                "number": 18, 
                "completed_at": "2020-10-07T18:30:10.000Z", 
                "started_at": "2020-10-07T18:30:10.000Z", 
                "conclusion": "success"
            }, 
            {
                "status": "completed", 
                "name": "Complete job", 
                "number": 19, 
                "completed_at": "2020-10-07T18:30:10.000Z", 
                "started_at": "2020-10-07T18:30:10.000Z", 
                "conclusion": "success"
            }
        ], 
        "head_sha": "abcb68288e4140d4b558bb7964f85bf78d45cb74", 
        "started_at": "2020-10-07T18:29:20Z", 
        "id": 1222121874, 
        "conclusion": "success"
    }, 
    {
        "status": "completed", 
        "check_run_url": "https://api.github.com/repos/rbsheth/hunter/check-runs/1222122011", 
        "name": "jpeg-compressor vs-14-2015-sdk-8-1 windows-2016", 
        "run_id": 293993383, 
        "url": "https://api.github.com/repos/rbsheth/hunter/actions/jobs/1222122011", 
        "html_url": "https://github.com/rbsheth/hunter/runs/1222122011", 
        "completed_at": "2020-10-07T18:31:59Z", 
        "run_url": "https://api.github.com/repos/rbsheth/hunter/actions/runs/293993383", 
        "node_id": "MDg6Q2hlY2tSdW4xMjIyMTIyMDEx", 
        "steps": [
            {
                "status": "completed", 
                "name": "Set up job", 
                "number": 1, 
                "completed_at": "2020-10-07T18:29:15.000Z", 
                "started_at": "2020-10-07T18:29:12.000Z", 
                "conclusion": "success"
            }, 
            {
                "status": "completed", 
                "name": "Git checkout with submodules", 
                "number": 2, 
                "completed_at": "2020-10-07T18:29:33.000Z", 
                "started_at": "2020-10-07T18:29:15.000Z", 
                "conclusion": "success"
            }, 
            {
                "status": "completed", 
                "name": "Set up Python", 
                "number": 3, 
                "completed_at": "2020-10-07T18:29:33.000Z", 
                "started_at": "2020-10-07T18:29:33.000Z", 
                "conclusion": "success"
            }, 
            {
                "status": "completed", 
                "name": "Set up Python environment variable (Unix)", 
                "number": 4, 
                "completed_at": "2020-10-07T18:29:33.000Z", 
                "started_at": "2020-10-07T18:29:33.000Z", 
                "conclusion": "skipped"
            }, 
            {
                "status": "completed", 
                "name": "Set up Python environment variable (Windows)", 
                "number": 5, 
                "completed_at": "2020-10-07T18:29:41.000Z", 
                "started_at": "2020-10-07T18:29:33.000Z", 
                "conclusion": "success"
            }, 
            {
                "status": "completed", 
                "name": "Extract branch name", 
                "number": 6, 
                "completed_at": "2020-10-07T18:29:41.000Z", 
                "started_at": "2020-10-07T18:29:41.000Z", 
                "conclusion": "success"
            }, 
            {
                "status": "completed", 
                "name": "Upgrade pip", 
                "number": 7, 
                "completed_at": "2020-10-07T18:29:47.000Z", 
                "started_at": "2020-10-07T18:29:41.000Z", 
                "conclusion": "success"
            }, 
            {
                "status": "completed", 
                "name": "Build on Unix", 
                "number": 8, 
                "completed_at": "2020-10-07T18:29:47.000Z", 
                "started_at": "2020-10-07T18:29:47.000Z", 
                "conclusion": "skipped"
            }, 
            {
                "status": "completed", 
                "name": "Build on Windows", 
                "number": 9, 
                "completed_at": "2020-10-07T18:31:56.000Z", 
                "started_at": "2020-10-07T18:29:47.000Z", 
                "conclusion": "success"
            }, 
            {
                "status": "completed", 
                "name": "Post Git checkout with submodules", 
                "number": 18, 
                "completed_at": "2020-10-07T18:31:59.000Z", 
                "started_at": "2020-10-07T18:31:56.000Z", 
                "conclusion": "success"
            }, 
            {
                "status": "completed", 
                "name": "Complete job", 
                "number": 19, 
                "completed_at": "2020-10-07T18:31:59.000Z", 
                "started_at": "2020-10-07T18:31:59.000Z", 
                "conclusion": "success"
            }
        ], 
        "head_sha": "abcb68288e4140d4b558bb7964f85bf78d45cb74", 
        "started_at": "2020-10-07T18:29:11Z", 
        "id": 1222122011, 
        "conclusion": "success"
    }, 
    {
        "status": "completed", 
        "check_run_url": "https://api.github.com/repos/rbsheth/hunter/check-runs/1222122002", 
        "name": "jpeg-compressor vs-15-2017-win64-cxx17 windows-2016", 
        "run_id": 293993383, 
        "url": "https://api.github.com/repos/rbsheth/hunter/actions/jobs/1222122002", 
        "html_url": "https://github.com/rbsheth/hunter/runs/1222122002", 
        "completed_at": "2020-10-07T18:31:43Z", 
        "run_url": "https://api.github.com/repos/rbsheth/hunter/actions/runs/293993383", 
        "node_id": "MDg6Q2hlY2tSdW4xMjIyMTIyMDAy", 
        "steps": [
            {
                "status": "completed", 
                "name": "Set up job", 
                "number": 1, 
                "completed_at": "2020-10-07T18:29:16.000Z", 
                "started_at": "2020-10-07T18:29:12.000Z", 
                "conclusion": "success"
            }, 
            {
                "status": "completed", 
                "name": "Git checkout with submodules", 
                "number": 2, 
                "completed_at": "2020-10-07T18:29:33.000Z", 
                "started_at": "2020-10-07T18:29:16.000Z", 
                "conclusion": "success"
            }, 
            {
                "status": "completed", 
                "name": "Set up Python", 
                "number": 3, 
                "completed_at": "2020-10-07T18:29:33.000Z", 
                "started_at": "2020-10-07T18:29:33.000Z", 
                "conclusion": "success"
            }, 
            {
                "status": "completed", 
                "name": "Set up Python environment variable (Unix)", 
                "number": 4, 
                "completed_at": "2020-10-07T18:29:33.000Z", 
                "started_at": "2020-10-07T18:29:33.000Z", 
                "conclusion": "skipped"
            }, 
            {
                "status": "completed", 
                "name": "Set up Python environment variable (Windows)", 
                "number": 5, 
                "completed_at": "2020-10-07T18:29:40.000Z", 
                "started_at": "2020-10-07T18:29:33.000Z", 
                "conclusion": "success"
            }, 
            {
                "status": "completed", 
                "name": "Extract branch name", 
                "number": 6, 
                "completed_at": "2020-10-07T18:29:41.000Z", 
                "started_at": "2020-10-07T18:29:40.000Z", 
                "conclusion": "success"
            }, 
            {
                "status": "completed", 
                "name": "Upgrade pip", 
                "number": 7, 
                "completed_at": "2020-10-07T18:29:46.000Z", 
                "started_at": "2020-10-07T18:29:41.000Z", 
                "conclusion": "success"
            }, 
            {
                "status": "completed", 
                "name": "Build on Unix", 
                "number": 8, 
                "completed_at": "2020-10-07T18:29:46.000Z", 
                "started_at": "2020-10-07T18:29:46.000Z", 
                "conclusion": "skipped"
            }, 
            {
                "status": "completed", 
                "name": "Build on Windows", 
                "number": 9, 
                "completed_at": "2020-10-07T18:31:40.000Z", 
                "started_at": "2020-10-07T18:29:46.000Z", 
                "conclusion": "success"
            }, 
            {
                "status": "completed", 
                "name": "Post Git checkout with submodules", 
                "number": 18, 
                "completed_at": "2020-10-07T18:31:43.000Z", 
                "started_at": "2020-10-07T18:31:40.000Z", 
                "conclusion": "success"
            }, 
            {
                "status": "completed", 
                "name": "Complete job", 
                "number": 19, 
                "completed_at": "2020-10-07T18:31:43.000Z", 
                "started_at": "2020-10-07T18:31:43.000Z", 
                "conclusion": "success"
            }
        ], 
        "head_sha": "abcb68288e4140d4b558bb7964f85bf78d45cb74", 
        "started_at": "2020-10-07T18:29:12Z", 
        "id": 1222122002, 
        "conclusion": "success"
    }, 
    {
        "status": "completed", 
        "check_run_url": "https://api.github.com/repos/rbsheth/hunter/check-runs/1222121992", 
        "name": "jpeg-compressor vs-16-2019-win64-cxx17 windows-2019", 
        "run_id": 293993383, 
        "url": "https://api.github.com/repos/rbsheth/hunter/actions/jobs/1222121992", 
        "html_url": "https://github.com/rbsheth/hunter/runs/1222121992", 
        "completed_at": "2020-10-07T18:31:19Z", 
        "run_url": "https://api.github.com/repos/rbsheth/hunter/actions/runs/293993383", 
        "node_id": "MDg6Q2hlY2tSdW4xMjIyMTIxOTky", 
        "steps": [
            {
                "status": "completed", 
                "name": "Set up job", 
                "number": 1, 
                "completed_at": "2020-10-07T18:29:13.000Z", 
                "started_at": "2020-10-07T18:29:12.000Z", 
                "conclusion": "success"
            }, 
            {
                "status": "completed", 
                "name": "Git checkout with submodules", 
                "number": 2, 
                "completed_at": "2020-10-07T18:29:29.000Z", 
                "started_at": "2020-10-07T18:29:13.000Z", 
                "conclusion": "success"
            }, 
            {
                "status": "completed", 
                "name": "Set up Python", 
                "number": 3, 
                "completed_at": "2020-10-07T18:29:29.000Z", 
                "started_at": "2020-10-07T18:29:29.000Z", 
                "conclusion": "success"
            }, 
            {
                "status": "completed", 
                "name": "Set up Python environment variable (Unix)", 
                "number": 4, 
                "completed_at": "2020-10-07T18:29:29.000Z", 
                "started_at": "2020-10-07T18:29:29.000Z", 
                "conclusion": "skipped"
            }, 
            {
                "status": "completed", 
                "name": "Set up Python environment variable (Windows)", 
                "number": 5, 
                "completed_at": "2020-10-07T18:29:40.000Z", 
                "started_at": "2020-10-07T18:29:29.000Z", 
                "conclusion": "success"
            }, 
            {
                "status": "completed", 
                "name": "Extract branch name", 
                "number": 6, 
                "completed_at": "2020-10-07T18:29:40.000Z", 
                "started_at": "2020-10-07T18:29:40.000Z", 
                "conclusion": "success"
            }, 
            {
                "status": "completed", 
                "name": "Upgrade pip", 
                "number": 7, 
                "completed_at": "2020-10-07T18:29:48.000Z", 
                "started_at": "2020-10-07T18:29:40.000Z", 
                "conclusion": "success"
            }, 
            {
                "status": "completed", 
                "name": "Build on Unix", 
                "number": 8, 
                "completed_at": "2020-10-07T18:29:48.000Z", 
                "started_at": "2020-10-07T18:29:48.000Z", 
                "conclusion": "skipped"
            }, 
            {
                "status": "completed", 
                "name": "Build on Windows", 
                "number": 9, 
                "completed_at": "2020-10-07T18:31:15.000Z", 
                "started_at": "2020-10-07T18:29:48.000Z", 
                "conclusion": "success"
            }, 
            {
                "status": "completed", 
                "name": "Post Git checkout with submodules", 
                "number": 18, 
                "completed_at": "2020-10-07T18:31:19.000Z", 
                "started_at": "2020-10-07T18:31:15.000Z", 
                "conclusion": "success"
            }, 
            {
                "status": "completed", 
                "name": "Complete job", 
                "number": 19, 
                "completed_at": "2020-10-07T18:31:19.000Z", 
                "started_at": "2020-10-07T18:31:19.000Z", 
                "conclusion": "success"
            }
        ], 
        "head_sha": "abcb68288e4140d4b558bb7964f85bf78d45cb74", 
        "started_at": "2020-10-07T18:29:12Z", 
        "id": 1222121992, 
        "conclusion": "success"
    }
]