[
    {
        "status": "completed", 
        "check_run_url": "https://api.github.com/repos/rbsheth/hunter/check-runs/1244107439", 
        "name": "meshoptimizer analyze-cxx17 ubuntu-16.04", 
        "run_id": 302852807, 
        "url": "https://api.github.com/repos/rbsheth/hunter/actions/jobs/1244107439", 
        "html_url": "https://github.com/rbsheth/hunter/runs/1244107439", 
        "completed_at": "2020-10-12T19:57:41Z", 
        "run_url": "https://api.github.com/repos/rbsheth/hunter/actions/runs/302852807", 
        "node_id": "MDg6Q2hlY2tSdW4xMjQ0MTA3NDM5", 
        "steps": [
            {
                "status": "completed", 
                "name": "Set up job", 
                "number": 1, 
                "completed_at": "2020-10-12T19:57:08.000Z", 
                "started_at": "2020-10-12T19:57:05.000Z", 
                "conclusion": "success"
            }, 
            {
                "status": "completed", 
                "name": "Git checkout with submodules", 
                "number": 2, 
                "completed_at": "2020-10-12T19:57:11.000Z", 
                "started_at": "2020-10-12T19:57:08.000Z", 
                "conclusion": "success"
            }, 
            {
                "status": "completed", 
                "name": "Set up Python", 
                "number": 3, 
                "completed_at": "2020-10-12T19:57:11.000Z", 
                "started_at": "2020-10-12T19:57:11.000Z", 
                "conclusion": "success"
            }, 
            {
                "status": "completed", 
                "name": "Set up Python environment variable (Unix)", 
                "number": 4, 
                "completed_at": "2020-10-12T19:57:11.000Z", 
                "started_at": "2020-10-12T19:57:11.000Z", 
                "conclusion": "success"
            }, 
            {
                "status": "completed", 
                "name": "Set up Python environment variable (Windows)", 
                "number": 5, 
                "completed_at": "2020-10-12T19:57:11.000Z", 
                "started_at": "2020-10-12T19:57:11.000Z", 
                "conclusion": "skipped"
            }, 
            {
                "status": "completed", 
                "name": "Extract branch name", 
                "number": 6, 
                "completed_at": "2020-10-12T19:57:11.000Z", 
                "started_at": "2020-10-12T19:57:11.000Z", 
                "conclusion": "success"
            }, 
            {
                "status": "completed", 
                "name": "Upgrade pip", 
                "number": 7, 
                "completed_at": "2020-10-12T19:57:15.000Z", 
                "started_at": "2020-10-12T19:57:11.000Z", 
                "conclusion": "success"
            }, 
            {
                "status": "completed", 
                "name": "Build on Unix", 
                "number": 8, 
                "completed_at": "2020-10-12T19:57:40.000Z", 
                "started_at": "2020-10-12T19:57:15.000Z", 
                "conclusion": "failure"
            }, 
            {
                "status": "completed", 
                "name": "Build on Windows", 
                "number": 9, 
                "completed_at": "2020-10-12T19:57:40.000Z", 
                "started_at": "2020-10-12T19:57:40.000Z", 
                "conclusion": "skipped"
            }, 
            {
                "status": "completed", 
                "name": "Post Git checkout with submodules", 
                "number": 18, 
                "completed_at": "2020-10-12T19:57:41.000Z", 
                "started_at": "2020-10-12T19:57:40.000Z", 
                "conclusion": "success"
            }, 
            {
                "status": "completed", 
                "name": "Complete job", 
                "number": 19, 
                "completed_at": "2020-10-12T19:57:41.000Z", 
                "started_at": "2020-10-12T19:57:41.000Z", 
                "conclusion": "success"
            }
        ], 
        "head_sha": "c97bdde5fad150b039ac45eabd8a7136ac9788a3", 
        "started_at": "2020-10-12T19:57:05Z", 
        "id": 1244107439, 
        "conclusion": "failure"
    }, 
    {
        "status": "completed", 
        "check_run_url": "https://api.github.com/repos/rbsheth/hunter/check-runs/1244107421", 
        "name": "meshoptimizer android-ndk-r17-api-24-arm64-v8a-clang-libcxx14 ubuntu-16.04", 
        "run_id": 302852807, 
        "url": "https://api.github.com/repos/rbsheth/hunter/actions/jobs/1244107421", 
        "html_url": "https://github.com/rbsheth/hunter/runs/1244107421", 
        "completed_at": "2020-10-12T19:58:21Z", 
        "run_url": "https://api.github.com/repos/rbsheth/hunter/actions/runs/302852807", 
        "node_id": "MDg6Q2hlY2tSdW4xMjQ0MTA3NDIx", 
        "steps": [
            {
                "status": "completed", 
                "name": "Set up job", 
                "number": 1, 
                "completed_at": "2020-10-12T19:57:10.000Z", 
                "started_at": "2020-10-12T19:57:06.000Z", 
                "conclusion": "success"
            }, 
            {
                "status": "completed", 
                "name": "Git checkout with submodules", 
                "number": 2, 
                "completed_at": "2020-10-12T19:57:17.000Z", 
                "started_at": "2020-10-12T19:57:10.000Z", 
                "conclusion": "success"
            }, 
            {
                "status": "completed", 
                "name": "Set up Python", 
                "number": 3, 
                "completed_at": "2020-10-12T19:57:17.000Z", 
                "started_at": "2020-10-12T19:57:17.000Z", 
                "conclusion": "success"
            }, 
            {
                "status": "completed", 
                "name": "Set up Python environment variable (Unix)", 
                "number": 4, 
                "completed_at": "2020-10-12T19:57:17.000Z", 
                "started_at": "2020-10-12T19:57:17.000Z", 
                "conclusion": "success"
            }, 
            {
                "status": "completed", 
                "name": "Set up Python environment variable (Windows)", 
                "number": 5, 
                "completed_at": "2020-10-12T19:57:17.000Z", 
                "started_at": "2020-10-12T19:57:17.000Z", 
                "conclusion": "skipped"
            }, 
            {
                "status": "completed", 
                "name": "Extract branch name", 
                "number": 6, 
                "completed_at": "2020-10-12T19:57:17.000Z", 
                "started_at": "2020-10-12T19:57:17.000Z", 
                "conclusion": "success"
            }, 
            {
                "status": "completed", 
                "name": "Upgrade pip", 
                "number": 7, 
                "completed_at": "2020-10-12T19:57:18.000Z", 
                "started_at": "2020-10-12T19:57:17.000Z", 
                "conclusion": "success"
            }, 
            {
                "status": "completed", 
                "name": "Build on Unix", 
                "number": 8, 
                "completed_at": "2020-10-12T19:58:20.000Z", 
                "started_at": "2020-10-12T19:57:18.000Z", 
                "conclusion": "success"
            }, 
            {
                "status": "completed", 
                "name": "Build on Windows", 
                "number": 9, 
                "completed_at": "2020-10-12T19:58:20.000Z", 
                "started_at": "2020-10-12T19:58:20.000Z", 
                "conclusion": "skipped"
            }, 
            {
                "status": "completed", 
                "name": "Post Git checkout with submodules", 
                "number": 18, 
                "completed_at": "2020-10-12T19:58:21.000Z", 
                "started_at": "2020-10-12T19:58:20.000Z", 
                "conclusion": "success"
            }, 
            {
                "status": "completed", 
                "name": "Complete job", 
                "number": 19, 
                "completed_at": "2020-10-12T19:58:21.000Z", 
                "started_at": "2020-10-12T19:58:21.000Z", 
                "conclusion": "success"
            }
        ], 
        "head_sha": "c97bdde5fad150b039ac45eabd8a7136ac9788a3", 
        "started_at": "2020-10-12T19:57:06Z", 
        "id": 1244107421, 
        "conclusion": "success"
    }, 
    {
        "status": "completed", 
        "check_run_url": "https://api.github.com/repos/rbsheth/hunter/check-runs/1244107350", 
        "name": "meshoptimizer clang-cxx17 ubuntu-16.04", 
        "run_id": 302852807, 
        "url": "https://api.github.com/repos/rbsheth/hunter/actions/jobs/1244107350", 
        "html_url": "https://github.com/rbsheth/hunter/runs/1244107350", 
        "completed_at": "2020-10-12T19:58:02Z", 
        "run_url": "https://api.github.com/repos/rbsheth/hunter/actions/runs/302852807", 
        "node_id": "MDg6Q2hlY2tSdW4xMjQ0MTA3MzUw", 
        "steps": [
            {
                "status": "completed", 
                "name": "Set up job", 
                "number": 1, 
                "completed_at": "2020-10-12T19:57:11.000Z", 
                "started_at": "2020-10-12T19:57:08.000Z", 
                "conclusion": "success"
            }, 
            {
                "status": "completed", 
                "name": "Git checkout with submodules", 
                "number": 2, 
                "completed_at": "2020-10-12T19:57:18.000Z", 
                "started_at": "2020-10-12T19:57:11.000Z", 
                "conclusion": "success"
            }, 
            {
                "status": "completed", 
                "name": "Set up Python", 
                "number": 3, 
                "completed_at": "2020-10-12T19:57:18.000Z", 
                "started_at": "2020-10-12T19:57:18.000Z", 
                "conclusion": "success"
            }, 
            {
                "status": "completed", 
                "name": "Set up Python environment variable (Unix)", 
                "number": 4, 
                "completed_at": "2020-10-12T19:57:19.000Z", 
                "started_at": "2020-10-12T19:57:18.000Z", 
                "conclusion": "success"
            }, 
            {
                "status": "completed", 
                "name": "Set up Python environment variable (Windows)", 
                "number": 5, 
                "completed_at": "2020-10-12T19:57:19.000Z", 
                "started_at": "2020-10-12T19:57:19.000Z", 
                "conclusion": "skipped"
            }, 
            {
                "status": "completed", 
                "name": "Extract branch name", 
                "number": 6, 
                "completed_at": "2020-10-12T19:57:19.000Z", 
                "started_at": "2020-10-12T19:57:19.000Z", 
                "conclusion": "success"
            }, 
            {
                "status": "completed", 
                "name": "Upgrade pip", 
                "number": 7, 
                "completed_at": "2020-10-12T19:57:21.000Z", 
                "started_at": "2020-10-12T19:57:19.000Z", 
                "conclusion": "success"
            }, 
            {
                "status": "completed", 
                "name": "Build on Unix", 
                "number": 8, 
                "completed_at": "2020-10-12T19:58:01.000Z", 
                "started_at": "2020-10-12T19:57:21.000Z", 
                "conclusion": "success"
            }, 
            {
                "status": "completed", 
                "name": "Build on Windows", 
                "number": 9, 
                "completed_at": "2020-10-12T19:58:01.000Z", 
                "started_at": "2020-10-12T19:58:01.000Z", 
                "conclusion": "skipped"
            }, 
            {
                "status": "completed", 
                "name": "Post Git checkout with submodules", 
                "number": 18, 
                "completed_at": "2020-10-12T19:58:02.000Z", 
                "started_at": "2020-10-12T19:58:01.000Z", 
                "conclusion": "success"
            }, 
            {
                "status": "completed", 
                "name": "Complete job", 
                "number": 19, 
                "completed_at": "2020-10-12T19:58:02.000Z", 
                "started_at": "2020-10-12T19:58:02.000Z", 
                "conclusion": "success"
            }
        ], 
        "head_sha": "c97bdde5fad150b039ac45eabd8a7136ac9788a3", 
        "started_at": "2020-10-12T19:57:08Z", 
        "id": 1244107350, 
        "conclusion": "success"
    }, 
    {
        "status": "completed", 
        "check_run_url": "https://api.github.com/repos/rbsheth/hunter/check-runs/1244107367", 
        "name": "meshoptimizer gcc-7-cxx17 ubuntu-16.04", 
        "run_id": 302852807, 
        "url": "https://api.github.com/repos/rbsheth/hunter/actions/jobs/1244107367", 
        "html_url": "https://github.com/rbsheth/hunter/runs/1244107367", 
        "completed_at": "2020-10-12T19:58:41Z", 
        "run_url": "https://api.github.com/repos/rbsheth/hunter/actions/runs/302852807", 
        "node_id": "MDg6Q2hlY2tSdW4xMjQ0MTA3MzY3", 
        "steps": [
            {
                "status": "completed", 
                "name": "Set up job", 
                "number": 1, 
                "completed_at": "2020-10-12T19:57:46.000Z", 
                "started_at": "2020-10-12T19:57:38.000Z", 
                "conclusion": "success"
            }, 
            {
                "status": "completed", 
                "name": "Git checkout with submodules", 
                "number": 2, 
                "completed_at": "2020-10-12T19:57:56.000Z", 
                "started_at": "2020-10-12T19:57:46.000Z", 
                "conclusion": "success"
            }, 
            {
                "status": "completed", 
                "name": "Set up Python", 
                "number": 3, 
                "completed_at": "2020-10-12T19:57:56.000Z", 
                "started_at": "2020-10-12T19:57:56.000Z", 
                "conclusion": "success"
            }, 
            {
                "status": "completed", 
                "name": "Set up Python environment variable (Unix)", 
                "number": 4, 
                "completed_at": "2020-10-12T19:57:56.000Z", 
                "started_at": "2020-10-12T19:57:56.000Z", 
                "conclusion": "success"
            }, 
            {
                "status": "completed", 
                "name": "Set up Python environment variable (Windows)", 
                "number": 5, 
                "completed_at": "2020-10-12T19:57:56.000Z", 
                "started_at": "2020-10-12T19:57:56.000Z", 
                "conclusion": "skipped"
            }, 
            {
                "status": "completed", 
                "name": "Extract branch name", 
                "number": 6, 
                "completed_at": "2020-10-12T19:57:56.000Z", 
                "started_at": "2020-10-12T19:57:56.000Z", 
                "conclusion": "success"
            }, 
            {
                "status": "completed", 
                "name": "Upgrade pip", 
                "number": 7, 
                "completed_at": "2020-10-12T19:58:00.000Z", 
                "started_at": "2020-10-12T19:57:56.000Z", 
                "conclusion": "success"
            }, 
            {
                "status": "completed", 
                "name": "Build on Unix", 
                "number": 8, 
                "completed_at": "2020-10-12T19:58:41.000Z", 
                "started_at": "2020-10-12T19:58:00.000Z", 
                "conclusion": "success"
            }, 
            {
                "status": "completed", 
                "name": "Build on Windows", 
                "number": 9, 
                "completed_at": "2020-10-12T19:58:41.000Z", 
                "started_at": "2020-10-12T19:58:41.000Z", 
                "conclusion": "skipped"
            }, 
            {
                "status": "completed", 
                "name": "Post Git checkout with submodules", 
                "number": 18, 
                "completed_at": "2020-10-12T19:58:41.000Z", 
                "started_at": "2020-10-12T19:58:41.000Z", 
                "conclusion": "success"
            }, 
            {
                "status": "completed", 
                "name": "Complete job", 
                "number": 19, 
                "completed_at": "2020-10-12T19:58:41.000Z", 
                "started_at": "2020-10-12T19:58:41.000Z", 
                "conclusion": "success"
            }
        ], 
        "head_sha": "c97bdde5fad150b039ac45eabd8a7136ac9788a3", 
        "started_at": "2020-10-12T19:57:38Z", 
        "id": 1244107367, 
        "conclusion": "success"
    }, 
    {
        "status": "completed", 
        "check_run_url": "https://api.github.com/repos/rbsheth/hunter/check-runs/1244107383", 
        "name": "meshoptimizer gcc-8-cxx17-fpic ubuntu-18.04", 
        "run_id": 302852807, 
        "url": "https://api.github.com/repos/rbsheth/hunter/actions/jobs/1244107383", 
        "html_url": "https://github.com/rbsheth/hunter/runs/1244107383", 
        "completed_at": "2020-10-12T19:58:15Z", 
        "run_url": "https://api.github.com/repos/rbsheth/hunter/actions/runs/302852807", 
        "node_id": "MDg6Q2hlY2tSdW4xMjQ0MTA3Mzgz", 
        "steps": [
            {
                "status": "completed", 
                "name": "Set up job", 
                "number": 1, 
                "completed_at": "2020-10-12T19:57:40.000Z", 
                "started_at": "2020-10-12T19:57:38.000Z", 
                "conclusion": "success"
            }, 
            {
                "status": "completed", 
                "name": "Git checkout with submodules", 
                "number": 2, 
                "completed_at": "2020-10-12T19:57:44.000Z", 
                "started_at": "2020-10-12T19:57:40.000Z", 
                "conclusion": "success"
            }, 
            {
                "status": "completed", 
                "name": "Set up Python", 
                "number": 3, 
                "completed_at": "2020-10-12T19:57:44.000Z", 
                "started_at": "2020-10-12T19:57:44.000Z", 
                "conclusion": "success"
            }, 
            {
                "status": "completed", 
                "name": "Set up Python environment variable (Unix)", 
                "number": 4, 
                "completed_at": "2020-10-12T19:57:44.000Z", 
                "started_at": "2020-10-12T19:57:44.000Z", 
                "conclusion": "success"
            }, 
            {
                "status": "completed", 
                "name": "Set up Python environment variable (Windows)", 
                "number": 5, 
                "completed_at": "2020-10-12T19:57:44.000Z", 
                "started_at": "2020-10-12T19:57:44.000Z", 
                "conclusion": "skipped"
            }, 
            {
                "status": "completed", 
                "name": "Extract branch name", 
                "number": 6, 
                "completed_at": "2020-10-12T19:57:44.000Z", 
                "started_at": "2020-10-12T19:57:44.000Z", 
                "conclusion": "success"
            }, 
            {
                "status": "completed", 
                "name": "Upgrade pip", 
                "number": 7, 
                "completed_at": "2020-10-12T19:57:48.000Z", 
                "started_at": "2020-10-12T19:57:44.000Z", 
                "conclusion": "success"
            }, 
            {
                "status": "completed", 
                "name": "Build on Unix", 
                "number": 8, 
                "completed_at": "2020-10-12T19:58:15.000Z", 
                "started_at": "2020-10-12T19:57:48.000Z", 
                "conclusion": "success"
            }, 
            {
                "status": "completed", 
                "name": "Build on Windows", 
                "number": 9, 
                "completed_at": "2020-10-12T19:58:15.000Z", 
                "started_at": "2020-10-12T19:58:15.000Z", 
                "conclusion": "skipped"
            }, 
            {
                "status": "completed", 
                "name": "Post Git checkout with submodules", 
                "number": 18, 
                "completed_at": "2020-10-12T19:58:15.000Z", 
                "started_at": "2020-10-12T19:58:15.000Z", 
                "conclusion": "success"
            }, 
            {
                "status": "completed", 
                "name": "Complete job", 
                "number": 19, 
                "completed_at": "2020-10-12T19:58:15.000Z", 
                "started_at": "2020-10-12T19:58:15.000Z", 
                "conclusion": "success"
            }
        ], 
        "head_sha": "c97bdde5fad150b039ac45eabd8a7136ac9788a3", 
        "started_at": "2020-10-12T19:57:38Z", 
        "id": 1244107383, 
        "conclusion": "success"
    }, 
    {
        "status": "completed", 
        "check_run_url": "https://api.github.com/repos/rbsheth/hunter/check-runs/1244107402", 
        "name": "meshoptimizer gcc-9-cxx17-fpic ubuntu-20.04", 
        "run_id": 302852807, 
        "url": "https://api.github.com/repos/rbsheth/hunter/actions/jobs/1244107402", 
        "html_url": "https://github.com/rbsheth/hunter/runs/1244107402", 
        "completed_at": "2020-10-12T19:58:15Z", 
        "run_url": "https://api.github.com/repos/rbsheth/hunter/actions/runs/302852807", 
        "node_id": "MDg6Q2hlY2tSdW4xMjQ0MTA3NDAy", 
        "steps": [
            {
                "status": "completed", 
                "name": "Set up job", 
                "number": 1, 
                "completed_at": "2020-10-12T19:57:42.000Z", 
                "started_at": "2020-10-12T19:57:39.000Z", 
                "conclusion": "success"
            }, 
            {
                "status": "completed", 
                "name": "Git checkout with submodules", 
                "number": 2, 
                "completed_at": "2020-10-12T19:57:45.000Z", 
                "started_at": "2020-10-12T19:57:42.000Z", 
                "conclusion": "success"
            }, 
            {
                "status": "completed", 
                "name": "Set up Python", 
                "number": 3, 
                "completed_at": "2020-10-12T19:57:45.000Z", 
                "started_at": "2020-10-12T19:57:45.000Z", 
                "conclusion": "success"
            }, 
            {
                "status": "completed", 
                "name": "Set up Python environment variable (Unix)", 
                "number": 4, 
                "completed_at": "2020-10-12T19:57:45.000Z", 
                "started_at": "2020-10-12T19:57:45.000Z", 
                "conclusion": "success"
            }, 
            {
                "status": "completed", 
                "name": "Set up Python environment variable (Windows)", 
                "number": 5, 
                "completed_at": "2020-10-12T19:57:45.000Z", 
                "started_at": "2020-10-12T19:57:45.000Z", 
                "conclusion": "skipped"
            }, 
            {
                "status": "completed", 
                "name": "Extract branch name", 
                "number": 6, 
                "completed_at": "2020-10-12T19:57:45.000Z", 
                "started_at": "2020-10-12T19:57:45.000Z", 
                "conclusion": "success"
            }, 
            {
                "status": "completed", 
                "name": "Upgrade pip", 
                "number": 7, 
                "completed_at": "2020-10-12T19:57:49.000Z", 
                "started_at": "2020-10-12T19:57:45.000Z", 
                "conclusion": "success"
            }, 
            {
                "status": "completed", 
                "name": "Build on Unix", 
                "number": 8, 
                "completed_at": "2020-10-12T19:58:14.000Z", 
                "started_at": "2020-10-12T19:57:49.000Z", 
                "conclusion": "success"
            }, 
            {
                "status": "completed", 
                "name": "Build on Windows", 
                "number": 9, 
                "completed_at": "2020-10-12T19:58:14.000Z", 
                "started_at": "2020-10-12T19:58:14.000Z", 
                "conclusion": "skipped"
            }, 
            {
                "status": "completed", 
                "name": "Post Git checkout with submodules", 
                "number": 18, 
                "completed_at": "2020-10-12T19:58:15.000Z", 
                "started_at": "2020-10-12T19:58:14.000Z", 
                "conclusion": "success"
            }, 
            {
                "status": "completed", 
                "name": "Complete job", 
                "number": 19, 
                "completed_at": "2020-10-12T19:58:15.000Z", 
                "started_at": "2020-10-12T19:58:15.000Z", 
                "conclusion": "success"
            }
        ], 
        "head_sha": "c97bdde5fad150b039ac45eabd8a7136ac9788a3", 
        "started_at": "2020-10-12T19:57:39Z", 
        "id": 1244107402, 
        "conclusion": "success"
    }, 
    {
        "status": "completed", 
        "check_run_url": "https://api.github.com/repos/rbsheth/hunter/check-runs/1244107451", 
        "name": "meshoptimizer sanitize-address-cxx17 ubuntu-16.04", 
        "run_id": 302852807, 
        "url": "https://api.github.com/repos/rbsheth/hunter/actions/jobs/1244107451", 
        "html_url": "https://github.com/rbsheth/hunter/runs/1244107451", 
        "completed_at": "2020-10-12T19:59:09Z", 
        "run_url": "https://api.github.com/repos/rbsheth/hunter/actions/runs/302852807", 
        "node_id": "MDg6Q2hlY2tSdW4xMjQ0MTA3NDUx", 
        "steps": [
            {
                "status": "completed", 
                "name": "Set up job", 
                "number": 1, 
                "completed_at": "2020-10-12T19:58:25.000Z", 
                "started_at": "2020-10-12T19:58:23.000Z", 
                "conclusion": "success"
            }, 
            {
                "status": "completed", 
                "name": "Git checkout with submodules", 
                "number": 2, 
                "completed_at": "2020-10-12T19:58:29.000Z", 
                "started_at": "2020-10-12T19:58:25.000Z", 
                "conclusion": "success"
            }, 
            {
                "status": "completed", 
                "name": "Set up Python", 
                "number": 3, 
                "completed_at": "2020-10-12T19:58:29.000Z", 
                "started_at": "2020-10-12T19:58:29.000Z", 
                "conclusion": "success"
            }, 
            {
                "status": "completed", 
                "name": "Set up Python environment variable (Unix)", 
                "number": 4, 
                "completed_at": "2020-10-12T19:58:29.000Z", 
                "started_at": "2020-10-12T19:58:29.000Z", 
                "conclusion": "success"
            }, 
            {
                "status": "completed", 
                "name": "Set up Python environment variable (Windows)", 
                "number": 5, 
                "completed_at": "2020-10-12T19:58:29.000Z", 
                "started_at": "2020-10-12T19:58:29.000Z", 
                "conclusion": "skipped"
            }, 
            {
                "status": "completed", 
                "name": "Extract branch name", 
                "number": 6, 
                "completed_at": "2020-10-12T19:58:29.000Z", 
                "started_at": "2020-10-12T19:58:29.000Z", 
                "conclusion": "success"
            }, 
            {
                "status": "completed", 
                "name": "Upgrade pip", 
                "number": 7, 
                "completed_at": "2020-10-12T19:58:33.000Z", 
                "started_at": "2020-10-12T19:58:29.000Z", 
                "conclusion": "success"
            }, 
            {
                "status": "completed", 
                "name": "Build on Unix", 
                "number": 8, 
                "completed_at": "2020-10-12T19:59:08.000Z", 
                "started_at": "2020-10-12T19:58:33.000Z", 
                "conclusion": "success"
            }, 
            {
                "status": "completed", 
                "name": "Build on Windows", 
                "number": 9, 
                "completed_at": "2020-10-12T19:59:08.000Z", 
                "started_at": "2020-10-12T19:59:08.000Z", 
                "conclusion": "skipped"
            }, 
            {
                "status": "completed", 
                "name": "Post Git checkout with submodules", 
                "number": 18, 
                "completed_at": "2020-10-12T19:59:09.000Z", 
                "started_at": "2020-10-12T19:59:08.000Z", 
                "conclusion": "success"
            }, 
            {
                "status": "completed", 
                "name": "Complete job", 
                "number": 19, 
                "completed_at": "2020-10-12T19:59:09.000Z", 
                "started_at": "2020-10-12T19:59:09.000Z", 
                "conclusion": "success"
            }
        ], 
        "head_sha": "c97bdde5fad150b039ac45eabd8a7136ac9788a3", 
        "started_at": "2020-10-12T19:58:23Z", 
        "id": 1244107451, 
        "conclusion": "success"
    }, 
    {
        "status": "completed", 
        "check_run_url": "https://api.github.com/repos/rbsheth/hunter/check-runs/1244107468", 
        "name": "meshoptimizer sanitize-leak-cxx17 ubuntu-16.04", 
        "run_id": 302852807, 
        "url": "https://api.github.com/repos/rbsheth/hunter/actions/jobs/1244107468", 
        "html_url": "https://github.com/rbsheth/hunter/runs/1244107468", 
        "completed_at": "2020-10-12T19:59:19Z", 
        "run_url": "https://api.github.com/repos/rbsheth/hunter/actions/runs/302852807", 
        "node_id": "MDg6Q2hlY2tSdW4xMjQ0MTA3NDY4", 
        "steps": [
            {
                "status": "completed", 
                "name": "Set up job", 
                "number": 1, 
                "completed_at": "2020-10-12T19:58:35.000Z", 
                "started_at": "2020-10-12T19:58:32.000Z", 
                "conclusion": "success"
            }, 
            {
                "status": "completed", 
                "name": "Git checkout with submodules", 
                "number": 2, 
                "completed_at": "2020-10-12T19:58:42.000Z", 
                "started_at": "2020-10-12T19:58:35.000Z", 
                "conclusion": "success"
            }, 
            {
                "status": "completed", 
                "name": "Set up Python", 
                "number": 3, 
                "completed_at": "2020-10-12T19:58:42.000Z", 
                "started_at": "2020-10-12T19:58:42.000Z", 
                "conclusion": "success"
            }, 
            {
                "status": "completed", 
                "name": "Set up Python environment variable (Unix)", 
                "number": 4, 
                "completed_at": "2020-10-12T19:58:42.000Z", 
                "started_at": "2020-10-12T19:58:42.000Z", 
                "conclusion": "success"
            }, 
            {
                "status": "completed", 
                "name": "Set up Python environment variable (Windows)", 
                "number": 5, 
                "completed_at": "2020-10-12T19:58:42.000Z", 
                "started_at": "2020-10-12T19:58:42.000Z", 
                "conclusion": "skipped"
            }, 
            {
                "status": "completed", 
                "name": "Extract branch name", 
                "number": 6, 
                "completed_at": "2020-10-12T19:58:42.000Z", 
                "started_at": "2020-10-12T19:58:42.000Z", 
                "conclusion": "success"
            }, 
            {
                "status": "completed", 
                "name": "Upgrade pip", 
                "number": 7, 
                "completed_at": "2020-10-12T19:58:45.000Z", 
                "started_at": "2020-10-12T19:58:42.000Z", 
                "conclusion": "success"
            }, 
            {
                "status": "completed", 
                "name": "Build on Unix", 
                "number": 8, 
                "completed_at": "2020-10-12T19:59:19.000Z", 
                "started_at": "2020-10-12T19:58:45.000Z", 
                "conclusion": "success"
            }, 
            {
                "status": "completed", 
                "name": "Build on Windows", 
                "number": 9, 
                "completed_at": "2020-10-12T19:59:19.000Z", 
                "started_at": "2020-10-12T19:59:19.000Z", 
                "conclusion": "skipped"
            }, 
            {
                "status": "completed", 
                "name": "Post Git checkout with submodules", 
                "number": 18, 
                "completed_at": "2020-10-12T19:59:19.000Z", 
                "started_at": "2020-10-12T19:59:19.000Z", 
                "conclusion": "success"
            }, 
            {
                "status": "completed", 
                "name": "Complete job", 
                "number": 19, 
                "completed_at": "2020-10-12T19:59:19.000Z", 
                "started_at": "2020-10-12T19:59:19.000Z", 
                "conclusion": "success"
            }
        ], 
        "head_sha": "c97bdde5fad150b039ac45eabd8a7136ac9788a3", 
        "started_at": "2020-10-12T19:58:32Z", 
        "id": 1244107468, 
        "conclusion": "success"
    }
]